{
  "sections": [
    {
      "id": "prologue",
      "kind": "prologue",
      "title": "소파는 도착했지만, 나는 아직 도착하지 않았다",
      "blocks": [
        {
          "type": "paragraph",
          "text": "이사는 끝났다."
        },
        {
          "type": "paragraph",
          "text": "현관 옆에는 아직 접지 않은 종이 상자가 두 개 남아 있었지만, 그것은 이사가 끝나지 않았다는 증거라기보다 이사를 끝냈다는 사람이 자신에게 허락하는 작은 유예에 가까웠다. 침대는 조립되었다. 인터넷은 연결되었다. 소파는 사진에서 본 것과 거의 같은 색이었다. 테이블 위에는 꽃병도 놓였다."
        },
        {
          "type": "paragraph",
          "text": "마지막으로 남은 것은 거실의 벽이었다."
        },
        {
          "type": "paragraph",
          "text": "그 벽이 비어 있어서 문제인 것은 아니었다. 빈 벽은 며칠쯤 참을 수 있다. 문제는 무엇을 걸어도 틀릴 것 같다는 데 있었다. 휴대전화에는 저장해 둔 방 사진이 수백 장 있었다. 추상화도 좋았고, 오래된 여행 포스터도 좋았다. 붓 자국이 큰 그림도, 여백이 많은 사진도 마음에 들었다. 좋아하는 것이 너무 많았다."
        },
        {
          "type": "paragraph",
          "text": "그러나 좋아하는 것과 함께 살 수 있는 것은 같은 말이 아니었다."
        },
        {
          "type": "paragraph",
          "text": "그녀는 작품 하나를 장바구니에 넣었다가 지웠다. 너무 무난했다. 다른 작품을 넣었다. 이번에는 너무 튀었다. 세 번째 작품은 예뻤지만 어느 카페에서 본 것 같았다. 네 번째 작품을 고를 무렵에는 처음에 무엇을 원했는지조차 흐릿해졌다. 결국 가장 확실한 선택을 했다. 아무것도 사지 않는 것이었다."
        },
        {
          "type": "paragraph",
          "text": "우리는 이런 일을 취향이 없어서 생긴다고 생각한다. 색을 잘 모르고, 미술을 모르고, 인테리어 감각이 부족해서 결정을 못 내린다고 여긴다. 그래서 더 찾아본다. 더 많은 방을 보고, 더 많은 스타일의 이름을 배우고, 더 많은 상품을 비교한다."
        },
        {
          "type": "paragraph",
          "text": "이 책의 주장은 반대다."
        },
        {
          "type": "quote",
          "text": "우리는 취향이 없어서 남의 집을 닮는 것이 아니다. 취향을 발견하는 도구는 넘치지만, 그것을 공간으로 번역하는 도구가 없어서다."
        },
        {
          "type": "paragraph",
          "text": "지난 10여 년 동안 우리는 취향을 발견하는 데 놀라울 만큼 능숙해졌다. 마음에 드는 이미지를 저장하고, 비슷한 이미지를 추천받고, 낯선 브랜드를 발견하고, 몇 초 만에 수십 개의 방을 훑어본다. 이제 아름다운 것을 만나기 위해 잡지 발행일을 기다리거나 가구 매장을 순회할 필요가 없다. 영감은 희귀한 자원이 아니다. 영감은 수도꼭지를 틀면 나오는 물처럼 풍부하다."
        },
        {
          "type": "paragraph",
          "text": "그런데 풍부해진 것은 영감이지 결정이 아니다."
        },
        {
          "type": "paragraph",
          "text": "우리가 저장한 이미지는 이것이 좋다고 말해 준다. 실제 방은 그렇다면 여기에는 무엇을 놓을 것인가라고 묻는다. 첫 번째 문장과 두 번째 문장 사이에는 생각보다 긴 거리가 있다. 그 거리에는 벽의 크기와 빛의 방향, 이미 가진 가구의 색, 예산, 기억, 함께 사는 사람, 실패하고 싶지 않은 마음이 들어 있다."
        },
        {
          "type": "paragraph",
          "text": "이 책은 그 거리를 번역의 공백이라고 부른다."
        },
        {
          "type": "paragraph",
          "text": "번역은 원문을 복사하는 일이 아니다. 한 언어에서 중요했던 의미를 다른 언어가 알아들을 수 있는 형태로 옮기는 일이다. 공간도 마찬가지다. 바닷가에서 보낸 한여름의 기억을 그대로 인쇄한다고 그 방에 여름이 생기는 것은 아니다. 그 기억에서 빛의 세기, 바람의 여백, 물의 리듬을 읽어 방의 색과 비율로 옮겨야 한다. 좋아하는 음악의 앨범 표지를 벽에 붙인다고 음악적인 공간이 되는 것도 아니다. 반복, 긴장, 침묵, 속도를 시각의 문법으로 바꾸어야 한다."
        },
        {
          "type": "paragraph",
          "text": "우리는 집에 놓을 물건을 고르는 시대에서 자신을 공간으로 번역하는 시대로 이동하고 있다."
        },
        {
          "type": "paragraph",
          "text": "그 변화가 지금 시작되는 데에는 이유가 있다. 취향은 이전보다 많은 흔적을 남긴다. 기계는 텍스트뿐 아니라 이미지와 방의 조건을 함께 다루기 시작했다. 하나의 결과도 재고 없이 생산하고 배송할 수 있다. 그리고 무한히 생성할 수 있게 된 바로 그 순간, 사람은 더 많은 결과가 아니라 고를 수 있는 확신을 필요로 하게 되었다."
        },
        {
          "type": "paragraph",
          "text": "그러므로 앞으로의 집을 바꿀 질문은 어떤 스타일을 좋아하세요?가 아닐 것이다."
        },
        {
          "type": "paragraph",
          "text": "더 나은 질문은 이것이다."
        },
        {
          "type": "quote",
          "text": "당신이 반복해서 사랑해 온 것은 무엇이며, 그것은 이 방에서 어떤 모습이어야 하는가?"
        },
        {
          "type": "paragraph",
          "text": "이 질문에 답하기 위해 먼저 이상한 집 하나를 들여다보아야 한다. 모든 것이 갖춰졌는데도 그 안에 사는 사람만 보이지 않는 집이다."
        }
      ]
    },
    {
      "id": "part-1",
      "kind": "part",
      "originalNumber": 1,
      "title": "완성된 방의 이상함",
      "blocks": []
    },
    {
      "id": "base-01",
      "kind": "chapter",
      "originalNumber": 1,
      "title": "집은 채워졌는데 사람은 보이지 않는다",
      "blocks": [
        {
          "type": "paragraph",
          "text": "숙박 시설의 방은 우리의 것이 아니어도 불편하지 않다. 우리는 그곳에 오래 머물 생각이 없기 때문이다. 침대보의 색이 나와 맞지 않아도 되고, 벽의 그림이 아무 의미가 없어도 된다. 그 방이 해야 할 일은 나를 표현하는 것이 아니라 하룻밤을 무사히 보내게 하는 것이다."
        },
        {
          "type": "paragraph",
          "text": "그런데 자신의 집이 숙박 시설처럼 느껴질 때는 문제가 달라진다."
        },
        {
          "type": "paragraph",
          "text": "깨끗하고 편리하다. 필요한 가구도 있다. 친구가 와서 예쁘다고 말한다. 사진을 찍으면 제법 근사하다. 그런데 혼자 남아 방을 바라보면 설명하기 어려운 이질감이 생긴다. 내 물건은 있는데 내 이야기는 없다. 잘못 꾸민 집은 아니지만, 내가 꾸민 집 같지도 않다."
        },
        {
          "type": "paragraph",
          "text": "나는 이런 집을 번역되지 않은 집이라고 부르려 한다."
        },
        {
          "type": "paragraph",
          "text": "번역되지 않은 집은 반드시 차갑거나 미니멀하지 않다. 물건이 아주 많을 수도 있고, 색이 화려할 수도 있다. 핵심은 장식의 양이 아니다. 그 물건들이 거주자의 삶과 어떤 관계를 맺는지 읽히지 않는다는 점이다. 유행하는 테이블, 인기 있는 조명, 무난한 포스터가 각자 훌륭하게 놓였지만 왜 이 사람이 이것들과 살아야 하는지는 알 수 없다."
        },
        {
          "type": "paragraph",
          "text": "집을 채우는 일과 집에 사람이 드러나는 일은 다르다."
        },
        {
          "type": "paragraph",
          "text": "전자는 목록으로 해결할 수 있다. 침대, 소파, 테이블, 수납장, 조명, 러그. 빠진 항목을 확인하고 예산 안에서 구매하면 된다. 후자는 목록이 아니라 해석을 요구한다. 이 사람은 무엇을 오래 기억하는가. 어떤 색 앞에서 속도를 늦추는가. 어디에서 편안함을 느끼는가. 무엇을 보면 자신이 지나온 시간을 떠올리는가."
        },
        {
          "type": "paragraph",
          "text": "오늘날의 유통은 첫 번째 문제를 매우 잘 해결한다. 검색창에 작은 거실 소파를 입력하면 크기, 가격, 색상, 배송일을 비교할 수 있다. 완성된 방 전체를 한 번에 구매하는 것도 가능하다. 한 이미지 속 소파와 테이블과 조명을 거의 그대로 따라 살 수 있다. 집을 기능적으로 완성하는 비용과 시간은 줄어들었다."
        },
        {
          "type": "paragraph",
          "text": "그 성공 때문에 두 번째 문제가 더 선명해졌다."
        },
        {
          "type": "paragraph",
          "text": "사람은 배가 고플 때 음식의 의미를 고민하지 않는다. 우선 먹는다. 마찬가지로 막 이사한 사람은 정체성을 번역하기 전에 침대를 산다. 그런데 기본적인 필요가 채워지고 나면 질문의 수준이 바뀐다. 무엇이 더 필요한가에서 왜 이곳이 아직 내 집 같지 않은가로 이동한다."
        },
        {
          "type": "paragraph",
          "text": "이때 벽이 자주 마지막 문제로 남는다. 벽은 소파보다 기능이 적고, 그래서 의미를 더 많이 요구한다. 소파는 앉으면 된다. 테이블은 물건을 올려놓으면 된다. 그러나 그림은 왜 이 그림이어야 하는지 묻는다. 기능으로 변명할 수 없는 물건은 취향을 드러낸다."
        },
        {
          "type": "paragraph",
          "text": "그래서 많은 사람이 벽 앞에서 오래 멈춘다. 작품이 비싸서만은 아니다. 잘못 고르면 돈을 잃는 것이 아니라 자신의 취향이 틀렸다는 판정을 받는 것처럼 느껴지기 때문이다. 옷은 하루 입고 바꿀 수 있지만, 거실 벽은 매일 같은 선택을 돌려준다. 벽에 거는 일은 생각보다 공개적인 자기 진술이다."
        },
        {
          "type": "paragraph",
          "text": "여기서 한 가지 오해를 피해야 한다. 모든 집이 거주자의 내면을 충실히 표현해야 한다는 뜻은 아니다. 집은 때로 그저 쉬는 곳이면 충분하다. 임시 거처에 큰 정서적 투자를 하지 않는 것도 합리적이다. 정체성을 표현하지 않는 선택 역시 하나의 선택이다."
        },
        {
          "type": "paragraph",
          "text": "문제는 표현하고 싶은데 방법을 모를 때 생긴다. 자신다운 집을 원하지만 시장이 제공하는 언어가 모던, 내추럴, 보헤미안 같은 스타일 분류뿐일 때, 사람은 자기 이야기를 상품 분류표에 맞추게 된다. 나를 설명하기 위해 집을 꾸미기 시작했는데, 끝나고 보면 내가 스타일을 설명하는 표본이 된다."
        },
        {
          "type": "paragraph",
          "text": "번역되지 않은 집의 문제는 아름다움이 부족하다는 것이 아니다. 관계가 부족하다는 것이다."
        },
        {
          "type": "paragraph",
          "text": "그렇다면 언제부터 우리는 집과 이런 관계를 기대하게 되었을까."
        }
      ]
    },
    {
      "id": "base-02",
      "kind": "chapter",
      "originalNumber": 2,
      "title": "집은 언제부터 자기소개가 되었나",
      "blocks": [
        {
          "type": "paragraph",
          "text": "집은 오랫동안 여러 역할을 동시에 해 왔다. 몸을 보호하는 구조물이었고, 가족이 모이는 장소였고, 노동이 이루어지는 곳이었으며, 자산이기도 했다. 새롭게 생긴 것은 집에 정체성이 있다는 생각 자체가 아니다. 사람은 오래전부터 집에 기억과 지위를 새겼다. 새로워진 것은 더 많은 사람이 더 자주, 더 의식적으로 집을 자기표현의 매체로 편집한다는 점이다."
        },
        {
          "type": "paragraph",
          "text": "예전의 자기소개는 대체로 몸과 말에 붙어 있었다. 무엇을 입는지, 어떤 일을 하는지, 어떤 음악을 듣는지, 어떤 사람들과 어울리는지가 한 사람을 설명했다. 이제 카메라가 일상의 거의 모든 곳에 들어오면서 집도 자기소개의 전면으로 나왔다. 영상 회의의 배경, 짧은 동영상의 촬영 장소, 온라인 중고 거래 사진의 한 귀퉁이까지 집은 의도하지 않아도 사람을 설명한다."
        },
        {
          "type": "paragraph",
          "text": "집은 가장 큰 프로필 사진이 되었다."
        },
        {
          "type": "paragraph",
          "text": "물론 이것을 소셜미디어만으로 설명하면 너무 간단하다. 우리가 집에서 기대하는 정서적 역할도 커졌다. 일하고, 운동하고, 쉬고, 사람을 만나고, 혼자 있는 일이 같은 공간에서 일어난다. 주거비가 많은 가구의 가장 큰 지출이라는 사실은 집이 경제적으로 얼마나 무거운 선택인지 보여 준다.〔1〕 비싸고 오래 머무는 공간일수록 사람은 그곳이 기능 이상의 것을 돌려주기를 기대한다. 안정감, 회복, 소속감, 때로는 자신이 제대로 살고 있다는 감각까지 말이다."
        },
        {
          "type": "paragraph",
          "text": "환경심리학은 오래전부터 주택과 집이 같은 말이 아니라고 보았다. 물리적 구조가 집으로 경험되기 위해서는 사생활, 관계, 지속성, 자기표현과 정체성 같은 요소가 필요하다는 연구가 있었다. 최근 주거 연구를 검토한 논문들도 장소 정체성, 장소 애착, 장소 의존이 공간을 집으로 바꾸는 핵심 층이라고 정리한다.〔2〕"
        },
        {
          "type": "paragraph",
          "text": "이 구분은 중요하다. 소유권이 집다움을 자동으로 만들지 않기 때문이다."
        },
        {
          "type": "paragraph",
          "text": "누군가는 10년째 임대한 작은 아파트를 자신의 역사로 채운다. 창가의 의자는 첫 직장에서 받은 월급으로 샀고, 벽의 사진은 혼자 떠난 여행에서 찍었으며, 식탁의 흠집은 오랜 친구들과 보낸 밤을 기억한다. 반대로 누군가는 큰돈을 들여 집을 샀지만 여전히 모델하우스 같은 낯섦 속에서 산다. 전자는 법적으로 남의 집일 수 있지만 정서적으로 자신의 집이다. 후자는 법적으로 자신의 집이지만 아직 자신에게 도착하지 않았다."
        },
        {
          "type": "paragraph",
          "text": "집다움은 등기부에서 생기지 않는다. 관계에서 생긴다."
        },
        {
          "type": "paragraph",
          "text": "우리는 물건에 기억을 저장한다. 오래된 머그잔은 도자기와 손잡이로만 이루어져 있지 않다. 어떤 아침, 어떤 사람, 어떤 시기를 함께 품는다. 공간도 같은 방식으로 기억을 저장한다. 특정 시간에 벽으로 기울어지는 빛, 현관문을 열었을 때 보이는 색, 반복해서 손이 닿는 표면은 몸의 기억이 된다."
        },
        {
          "type": "paragraph",
          "text": "이 때문에 집을 개인화한다는 말은 단순히 이름을 새기거나 좋아하는 색을 고르는 것보다 깊다. 개인화는 나와 관계없는 물건을 내 취향처럼 보이게 하는 일이 아니다. 나에게 이미 의미 있는 것을 공간이 알아들을 수 있게 만드는 일이다."
        },
        {
          "type": "paragraph",
          "text": "하지만 시장이 말하는 개인화는 흔히 선택 항목을 늘리는 데 머문다. 색상 열두 개, 크기 여섯 개, 프레임 네 개를 고를 수 있으면 개인화되었다고 부른다. 선택권은 늘었지만 질문은 바뀌지 않는다. 어느 색을 원하세요?라고 묻지, 왜 그 색이 당신에게 남았나요?라고 묻지 않는다."
        },
        {
          "type": "paragraph",
          "text": "집이 자기소개가 되었다면, 홈데코의 다음 과제는 상품의 변형이 아니라 사람의 해석이어야 한다."
        },
        {
          "type": "paragraph",
          "text": "여기서 집의 의미는 다시 바뀐다. 첫 집은 더 이상 처음 산 부동산만을 뜻하지 않는다. 처음으로 자기 삶을 공간에 의도적으로 쓰기 시작한 장소가 된다."
        }
      ]
    },
    {
      "id": "base-03",
      "kind": "chapter",
      "originalNumber": 3,
      "title": "첫 자가보다 먼저 오는 첫 개인적 집",
      "blocks": [
        {
          "type": "paragraph",
          "text": "첫 집이라는 말에는 대개 열쇠를 건네받는 장면이 따라온다. 계약서에 서명하고, 현관 앞에서 사진을 찍고, 이제 집주인이 되었다고 말하는 순간이다. 이 서사는 여전히 강력하다. 그러나 점점 더 많은 사람에게 첫 집은 늦게 오거나, 다른 모습으로 오거나, 아예 소유권과 함께 오지 않는다."
        },
        {
          "type": "paragraph",
          "text": "미국에서 2025년 첫 주택 구매자의 중위 연령은 40세까지 올라갔다.〔3〕 캐나다의 25~39세 밀레니얼은 같은 나이였던 이전 세대보다 부모와 함께 사는 비율이 높고, 주거 경로도 더 다양해졌다.〔4〕 영국의 민간 임대 가구 기준으로 보면 25~34세와 35~44세가 큰 비중을 차지한다.〔5〕 이 숫자들은 세 나라의 제도와 시장이 같다는 뜻이 아니다. 공통으로 읽을 수 있는 것은 성인의 삶과 주거의 전통적인 시간표가 느슨해졌다는 점이다."
        },
        {
          "type": "paragraph",
          "text": "그렇다면 우리는 첫 집을 소유의 사건이 아니라 의도의 사건으로 다시 정의할 수 있다."
        },
        {
          "type": "quote",
          "text": "첫 개인적 집은 처음 소유한 집이 아니라, 처음으로 자신을 담기로 결심한 집이다."
        },
        {
          "type": "paragraph",
          "text": "첫 개인적 집은 여러 순간에 찾아온다."
        },
        {
          "type": "paragraph",
          "text": "계약을 한 번 더 연장하면서 이곳을 잠깐 거쳐 가는 방으로 대하지 않기로 할 때. 연인과 함께 살기 시작하며 두 사람의 물건 사이에 공동의 언어를 만들어야 할 때. 이별 뒤 혼자 남은 공간에서 타인의 흔적을 지우는 것보다 자신의 흔적을 새기는 일이 더 중요해질 때. 일을 집으로 가져오면서 카메라에 잡히는 배경이 아니라 실제로 집중할 수 있는 장소가 필요해질 때. 오래 기다린 끝에 집을 샀지만 이전 임대 주택에서 가져온 가구만으로는 새 삶이 설명되지 않을 때."
        },
        {
          "type": "paragraph",
          "text": "첫 개인적 집의 공통점은 주소가 아니라 전환이다."
        },
        {
          "type": "paragraph",
          "text": "전환기에는 사람이 자신을 다시 설명해야 한다. 나는 이제 누구와 사는가. 무엇을 집에서 하는가. 어떤 시간을 지나왔는가. 앞으로 어떤 사람으로 살고 싶은가. 옷장을 정리하고 가구를 옮기는 일은 이 질문에 대한 물리적 답변이 된다."
        },
        {
          "type": "paragraph",
          "text": "그래서 홈데코 구매는 생애 사건과 가까이 붙어 있다. 사람은 늘 아름다운 것을 원하지만, 모든 시기에 같은 강도로 집을 바꾸지는 않는다. 현재의 공간과 현재의 자아 사이의 차이가 커질 때 움직인다. 이사, 동거, 결혼, 이별, 출산, 독립, 이직, 재택근무, 회복. 이런 사건은 방을 낡게 만들지 않지만, 방의 의미를 낡게 만든다."
        },
        {
          "type": "paragraph",
          "text": "여기에는 흥미로운 역설이 있다. 주거가 비싸고 불안정할수록 사람은 공간에 덜 투자할 것 같지만, 동시에 같은 이유로 더 많은 정서적 보상을 원할 수 있다. 쉽게 옮길 수 없는 사람은 지금 있는 곳을 견딜 만하게 만들고 싶다. 큰 비용을 치른 사람은 이 공간이 그만한 의미를 갖기를 바란다. 임대라서 아무것도 하지 않는 사람도 있지만, 임대이기 때문에 이동 가능한 방식으로 자신을 담으려는 사람도 있다."
        },
        {
          "type": "paragraph",
          "text": "작품은 이 조건에 잘 맞는다. 구조를 바꾸지 않고도 방의 중심을 바꿀 수 있다. 이사할 때 가져갈 수 있다. 가구보다 작은 비용으로 분위기를 크게 바꾸고, 기능이 적은 만큼 의미를 많이 담을 수 있다. 동시에 바로 그 이유로 고르기 어렵다. 기능적 비교가 어려워서 취향과 확신이 더 필요하다."
        },
        {
          "type": "paragraph",
          "text": "첫 개인적 집을 만드는 사람에게 필요한 것은 완성된 스타일 세트가 아니다. 과거의 자신, 현재의 방, 앞으로의 삶을 함께 읽어 주는 방법이다."
        },
        {
          "type": "paragraph",
          "text": "그런데 우리는 이미 그 어느 때보다 많은 스타일과 이미지를 갖고 있다. 왜 그 많은 영감은 이 문제를 해결하지 못했을까."
        }
      ]
    },
    {
      "id": "part-2",
      "kind": "part",
      "originalNumber": 2,
      "title": "영감의 풍요, 번역의 빈곤",
      "blocks": []
    },
    {
      "id": "base-04",
      "kind": "chapter",
      "originalNumber": 4,
      "title": "예쁜 집을 너무 많이 본 사람들",
      "blocks": [
        {
          "type": "paragraph",
          "text": "잠들기 전 열어 본 방 하나가 마음에 든다. 천장이 높고, 오후의 빛이 길게 들어오고, 짙은 초록색 의자 옆에 작은 그림이 걸려 있다. 저장한다. 손가락을 한 번 더 움직이면 비슷한 방이 나온다. 이번에는 벽이 분홍색이다. 저장한다. 다음 방에는 낮은 소파와 커다란 추상화가 있다. 그것도 저장한다."
        },
        {
          "type": "paragraph",
          "text": "몇 분 뒤 우리는 서로 양립하기 어려운 열두 개의 삶을 저장해 두었다."
        },
        {
          "type": "paragraph",
          "text": "산장이 되고 싶은 삶, 파리의 오래된 아파트가 되고 싶은 삶, 해변의 흰 집이 되고 싶은 삶, 창고를 개조한 스튜디오가 되고 싶은 삶. 화면에서는 모두 가능하다. 화면을 닫으면 하나의 방만 남는다. 천장은 낮고, 창은 북쪽을 향하며, 이미 산 회색 소파가 예상보다 크다."
        },
        {
          "type": "paragraph",
          "text": "영감 산업은 실패하지 않았다. 너무 성공했다."
        },
        {
          "type": "paragraph",
          "text": "Pinterest는 2026년 1분기에 전 세계 월간 활성 이용자 6억 3,100만 명과 월간 검색 800억 건 이상을 보고했다. 검색의 약 절반은 상업적 성격을 띤다고 밝혔다.〔6〕 이 숫자가 보여 주는 것은 특정 플랫폼의 크기만이 아니다. 사람에게는 보고, 저장하고, 계획하고, 언젠가 구매하려는 거대한 행동이 이미 있다는 뜻이다."
        },
        {
          "type": "paragraph",
          "text": "과거에는 취향을 발견하려면 문지기가 필요했다. 잡지 편집자가 골라 준 집을 보거나, 매장에 진열된 상품 중에서 선택하거나, 전문가가 제시한 견본을 따라야 했다. 지금은 작은 도시의 임대 아파트에서도 세계 곳곳의 방을 볼 수 있다. 낯선 작가와 독립 브랜드를 발견하고, 이전에는 이름조차 몰랐던 색과 재료를 배운다."
        },
        {
          "type": "paragraph",
          "text": "이것은 분명한 진보다. 더 많은 사람이 아름다움에 접근하고 자기 취향을 탐색하게 되었다."
        },
        {
          "type": "paragraph",
          "text": "그러나 발견의 민주화가 적용의 민주화를 자동으로 만들지는 않았다."
        },
        {
          "type": "paragraph",
          "text": "화면 속 방은 대개 맥락과 함께 편집된 결과다. 적절한 시간의 빛, 촬영을 위한 정돈, 프레임 밖으로 치운 물건, 넓어 보이게 하는 렌즈, 이미 조화를 이룬 건축과 가구가 한 장면을 만든다. 우리는 그 결과에서 의자 하나나 그림 하나를 떼어 와 자신의 방에도 같은 감정이 생기기를 기대한다."
        },
        {
          "type": "paragraph",
          "text": "하지만 감정은 상품에 단독으로 들어 있지 않다. 관계에서 생긴다."
        },
        {
          "type": "paragraph",
          "text": "같은 주황색 의자도 흰 벽과 짙은 나무 바닥 사이에서는 따뜻한 중심이 되지만, 붉은 바닥과 노란 조명 아래에서는 피곤한 소음이 될 수 있다. 같은 사진도 좁은 복도에서는 창문처럼 작동하고, 큰 거실에서는 사라져 보일 수 있다. 상품의 아름다움은 고정된 속성이 아니라 주변과 맺는 관계다."
        },
        {
          "type": "paragraph",
          "text": "영감 플랫폼은 무엇을 좋아할 수 있는가를 탁월하게 보여 준다. 그러나 이것이 지금 내 방에서 어떻게 작동할 것인가에는 제한적으로 답한다. 그 질문에는 방의 사진뿐 아니라 그 사람이 이미 가진 것, 바꾸지 못하는 것, 중요하게 여기는 것까지 필요하기 때문이다."
        },
        {
          "type": "paragraph",
          "text": "그래서 저장은 종종 결정이 아니라 결정의 연기가 된다. 우리는 더 알아보기 위해 저장한다고 생각하지만, 때로는 선택하지 않기 위해 저장한다. 오늘 결론을 내리지 않아도 취향 있는 사람처럼 느낄 수 있는 작은 행동이다. 저장 목록은 집을 만들기 위한 자료이면서, 만들지 못한 집들의 보관소가 된다."
        },
        {
          "type": "paragraph",
          "text": "이것을 플랫폼의 잘못이라고 말할 수는 없다. 지도는 목적지를 보여 주지만 대신 걸어 주지 않는다. 영감의 역할도 그렇다. 문제는 지도에게 번역가의 일을 기대할 때 생긴다."
        },
        {
          "type": "paragraph",
          "text": "영감은 필요하다. 그러나 영감은 번역이 아니다."
        },
        {
          "type": "paragraph",
          "text": "우리는 이 차이를 오랫동안 선택지의 수로 덮어 왔다. 마음에 드는 것이 없다면 더 보여 주면 된다고 생각했다. 결과는 역설적이다. 예쁜 집을 너무 많이 본 사람은 예쁜 것을 알아보는 눈은 좋아졌지만, 자신의 집에 무엇이 속하는지를 결정하는 일은 더 어려워질 수 있다."
        },
        {
          "type": "paragraph",
          "text": "더구나 이미지가 많아질수록 특정한 몇 가지 스타일은 더 빠르게 복제된다. 영감을 찾아 떠난 사람이 어느 순간 카탈로그의 언어로 자신을 설명하기 시작한다."
        }
      ]
    },
    {
      "id": "base-05",
      "kind": "chapter",
      "originalNumber": 5,
      "title": "카탈로그가 우리 대신 취향을 말할 때",
      "blocks": [
        {
          "type": "paragraph",
          "text": "당신의 인테리어 스타일을 찾아보세요."
        },
        {
          "type": "paragraph",
          "text": "질문은 친절하다. 몇 장의 이미지 중 마음에 드는 것을 고르면 결과가 나온다. 미드센추리 모던, 스칸디나비안, 재팬디, 보헤미안, 인더스트리얼. 이름을 얻는 순간 안도감이 생긴다. 혼란스러웠던 선호가 하나의 폴더에 정리된다. 이제 무엇을 검색해야 하는지 알 것 같다."
        },
        {
          "type": "paragraph",
          "text": "스타일은 취향을 압축하는 훌륭한 기술이다."
        },
        {
          "type": "paragraph",
          "text": "한 단어 안에 시대, 재료, 형태, 색, 브랜드, 생활방식의 묶음을 담는다. 판매자는 상품을 분류할 수 있고, 구매자는 낯선 영역을 빠르게 탐색할 수 있다. 디자이너와 고객이 공통의 출발점을 갖게 된다. 스타일 이름이 없었다면 모든 대화는 훨씬 오래 걸렸을 것이다."
        },
        {
          "type": "paragraph",
          "text": "문제는 압축 파일을 사람 자체로 착각할 때 생긴다."
        },
        {
          "type": "paragraph",
          "text": "한 사람은 오래된 목재의 흔적을 좋아하면서도 장식적인 가구는 싫어할 수 있다. 강한 원색을 좋아하지만 집에서는 조용함을 원할 수 있다. 여행에서는 붐비는 도시를 사랑하고, 귀가한 뒤에는 여백이 많은 방에서 쉬고 싶을 수 있다. 취향은 일관된 브랜드 가이드가 아니다. 서로 다른 욕구가 상황에 따라 협상하는 과정에 가깝다."
        },
        {
          "type": "paragraph",
          "text": "스타일 분류는 이 모순을 불편해한다. 카테고리는 경계를 필요로 한다. 이 상품이 어느 선반에 놓여야 하는지 결정해야 한다. 반면 사람의 취향은 경계를 넘나든다. 할머니 집의 자개장과 최신식 금속 조명을 동시에 좋아한다. 사막의 색과 북유럽 가구를 함께 기억한다. 일관되지 않아서 틀린 것이 아니라, 삶이 여러 시간과 장소로 이루어져 있기 때문에 그렇다."
        },
        {
          "type": "paragraph",
          "text": "카탈로그는 우리에게 물건을 고르는 법을 가르쳤지만, 자신을 읽는 법까지 가르치지는 않았다."
        },
        {
          "type": "paragraph",
          "text": "이 차이는 완성된 방에서 드러난다. 특정 스타일의 규칙을 정확히 지킨 방은 조화롭다. 색은 충돌하지 않고, 재료는 같은 시대를 말하며, 사진으로도 잘 읽힌다. 그런데 거주자의 삶을 묻기 시작하면 대답이 줄어든다. 왜 이 그림인가. 이 색은 무엇을 떠올리게 하는가. 이 물건은 어떤 시간을 지나왔는가."
        },
        {
          "type": "paragraph",
          "text": "질문이 많아질수록 방은 침묵한다."
        },
        {
          "type": "paragraph",
          "text": "유행을 비판하는 것은 쉽다. 모두가 비슷한 소파를 사고 같은 포스터를 건다고 비웃을 수도 있다. 그러나 대량 유통과 카탈로그는 좋은 디자인을 더 많은 사람에게 열어 주었다. 문제는 대중적인 물건을 사는 데 있지 않다. 관계없이 사는 데 있다. 수백만 명이 같은 의자를 사더라도 각자의 삶과 다른 관계를 맺을 수 있다."
        },
        {
          "type": "paragraph",
          "text": "개성은 희귀한 물건의 수가 아니다. 평범한 물건까지 자기 삶의 문장 안에 놓는 방식이다."
        },
        {
          "type": "paragraph",
          "text": "그럼에도 시장은 계속 당신과 비슷한 사람들이 산 것을 추천한다. 추천 시스템은 과거의 집단 행동에서 다음 선택을 예측한다. 이 방식은 편리하고 자주 정확하다. 그러나 비슷한 사람이 산 것을 반복해서 보여 주면 발견은 어느 순간 수렴이 된다. 추천은 나를 알아보는 듯하다가, 나를 이미 존재하는 집단의 평균으로 되돌려 놓는다."
        },
        {
          "type": "paragraph",
          "text": "이때 개인화라는 말은 묘하게 뒤집힌다. 나에게 맞춘 추천을 많이 받을수록 나와 비슷한 사람들의 방과 닮아 갈 수 있다. 개인화된 유사성이다."
        },
        {
          "type": "paragraph",
          "text": "공간번역은 스타일을 없애려는 시도가 아니다. 스타일을 문장의 끝이 아니라 재료 중 하나로 되돌리는 일이다. 나는 재팬디를 좋아한다에서 멈추지 않고, 그 안에서 무엇을 좋아하는지 묻는다. 낮은 가구인가, 절제된 색인가, 불완전한 표면인가, 비어 있는 공간인가. 그리고 왜 그것이 지금의 삶에 필요한지 묻는다."
        },
        {
          "type": "paragraph",
          "text": "스타일은 답이 아니라 단서다."
        },
        {
          "type": "paragraph",
          "text": "이렇게 보면 취향이 없다는 말도 다시 생각해야 한다. 사람에게 취향이 없는 것이 아니라, 자신이 남긴 단서를 한 문장으로 묶는 문법이 없을 수 있다."
        }
      ]
    },
    {
      "id": "base-06",
      "kind": "chapter",
      "originalNumber": 6,
      "title": "우리는 취향이 없는 것이 아니라 문법이 없다",
      "blocks": [
        {
          "type": "paragraph",
          "text": "누군가에게 좋아하는 색을 물으면 파란색이라고 답할 수 있다. 그러나 파란색은 충분한 답이 아니다. 겨울 새벽의 잿빛 파랑과 한낮 수영장의 파랑은 같은 이름 아래 전혀 다른 감정을 가진다. 광택 있는 금속 위의 파랑과 바랜 천의 파랑도 다르다. 색의 이름만으로는 그 사람이 무엇을 좋아하는지 알 수 없다."
        },
        {
          "type": "paragraph",
          "text": "좋아하는 장소를 물어도 마찬가지다. 바다라는 답은 수평선의 여백을 뜻할 수도 있고, 소금기 있는 바람을 뜻할 수도 있으며, 어린 시절 가족과 보낸 시간을 뜻할 수도 있다. 어떤 사람에게 바다는 고요함이고, 다른 사람에게는 몸을 압도하는 힘이다."
        },
        {
          "type": "paragraph",
          "text": "취향은 명사보다 관계에 숨어 있다."
        },
        {
          "type": "paragraph",
          "text": "우리는 자신이 좋아하는 사물의 목록을 어느 정도 알고 있다. 문제는 그 목록에서 반복되는 감각을 읽고 실제 공간의 결정으로 바꾸는 일이다. 이 과정에는 세 가지 언어가 등장한다."
        },
        {
          "type": "paragraph",
          "text": "첫째는 사람의 언어다. 장소, 음악, 기억, 색, 물건, 이야기처럼 삶에 붙어 있는 단서다."
        },
        {
          "type": "paragraph",
          "text": "둘째는 공간의 언어다. 빛, 비율, 크기, 재료, 여백, 시선, 기존 가구와 같이 방이 가진 조건이다."
        },
        {
          "type": "paragraph",
          "text": "셋째는 선택의 언어다. 무엇을 고를지, 왜 그것이 맞는지, 돈을 내고 함께 살 만큼 확신할 수 있는지에 관한 판단이다."
        },
        {
          "type": "paragraph",
          "text": "공간번역은 이 세 언어 사이를 오가는 일이다."
        },
        {
          "type": "quote",
          "text": "정체성 단서 + 실제 공간 + 선택의 확신 = 공간번역"
        },
        {
          "type": "paragraph",
          "text": "예를 들어 한 사람이 교토의 작은 골목을 좋아한다고 하자. 나쁜 번역은 골목 사진을 크게 인쇄하는 것이다. 틀린 것은 아니지만 가장 표면적인 대응이다. 더 나은 번역은 왜 그 장소가 남았는지 묻는다. 빗물에 어두워진 돌, 낮은 처마, 안쪽에서 새어 나오는 따뜻한 빛, 좁은 길 끝의 여백이 중요했다면 결과는 사진이 아니라 어두운 질감과 작은 빛의 대비, 수직으로 긴 구성으로 나타날 수 있다."
        },
        {
          "type": "paragraph",
          "text": "같은 기억도 방에 따라 달라진다. 이미 짙은 나무와 따뜻한 조명이 있는 방에서는 그 기억의 온기를 더하는 방향이 지나칠 수 있다. 차가운 금속과 흰 벽이 많은 방이라면 작은 따뜻함이 중심이 될 수 있다. 사람의 단서를 충실히 옮기는 일과 방에 잘 어울리게 만드는 일은 때때로 충돌한다. 번역은 둘 중 하나를 포기하는 것이 아니라 관계를 조정한다."
        },
        {
          "type": "paragraph",
          "text": "여기에 선택의 확신이 빠지면 번역은 화면 속 실험으로 끝난다. 멋진 결과를 보고도 정말 나다운가, 실제로 걸면 괜찮을까, 곧 싫증 나지 않을까라는 질문이 남는다. 개인화된 결과를 많이 보여 주는 것만으로는 부족하다. 왜 이런 해석이 나왔는지 이해하고, 실제 방 안에서 크기와 관계를 보고, 다른 방향과 비교할 수 있어야 한다."
        },
        {
          "type": "paragraph",
          "text": "공간번역은 예술가의 영감을 자동화하는 말이 아니다. 인테리어 디자이너의 일을 한 번의 클릭으로 대체한다는 약속도 아니다. 더 좁고 현실적인 제안이다. 지금까지 서로 떨어져 있던 사람의 단서와 방의 조건과 구매의 확신을 하나의 흐름으로 연결할 수 있지 않겠느냐는 가설이다."
        },
        {
          "type": "paragraph",
          "text": "이 가설은 취향을 완벽히 설명할 필요가 없다. 번역은 원문과 완전히 같을 수 없고, 좋은 번역도 유일하지 않다. 중요한 것은 사람에게 낯선 정답을 선고하는 것이 아니라, 자신이 알아볼 수 있는 몇 가지 해석을 건네는 것이다."
        },
        {
          "type": "paragraph",
          "text": "그런데 왜 이 일이 이제야 제품의 형태로 가능해졌을까."
        },
        {
          "type": "paragraph",
          "text": "첫 번째 이유는 사람이 갑자기 더 많은 취향을 갖게 되어서가 아니다. 취향이 이전보다 훨씬 많은 흔적을 남기기 시작했기 때문이다."
        }
      ]
    },
    {
      "id": "part-3",
      "kind": "part",
      "originalNumber": 3,
      "title": "왜 지금 공간번역인가",
      "blocks": []
    },
    {
      "id": "base-07",
      "kind": "chapter",
      "originalNumber": 7,
      "title": "취향은 흔적을 남기기 시작했다",
      "blocks": [
        {
          "type": "paragraph",
          "text": "사람은 자신을 설명하는 데 서툴다. 특히 취향 앞에서 그렇다."
        },
        {
          "type": "paragraph",
          "text": "어떤 분위기를 좋아하세요?라고 물으면 많은 사람이 따뜻하지만 답답하지 않고, 심플하지만 너무 비어 보이지 않는 같은 답을 한다. 모순처럼 들리지만 사실 꽤 정확한 말이다. 사람은 따뜻함과 여백을 함께 원한다. 문제는 그 말을 구체적인 시각 결정으로 옮기기 어렵다는 데 있다."
        },
        {
          "type": "paragraph",
          "text": "반면 행동은 말보다 자세한 기록을 남긴다."
        },
        {
          "type": "paragraph",
          "text": "몇 년 동안 저장한 이미지에는 반복되는 빛이 있다. 여행 사진에는 자주 프레임 안에 들어오는 재료가 있다. 플레이리스트에는 특정한 속도와 밀도가 있다. 좋아하는 옷에는 자주 손이 가는 색과 질감이 있다. 말로는 아무거나 괜찮다고 하는 사람도 실제 선택에서는 아무거나 고르지 않는다."
        },
        {
          "type": "paragraph",
          "text": "취향이 새로 생긴 것이 아니다. 흔적의 양이 달라졌다."
        },
        {
          "type": "paragraph",
          "text": "필름 사진 시절에도 사람은 좋아하는 장면을 찍었다. 잡지의 페이지를 오려 보드에 붙이기도 했다. 그러나 지금은 발견과 저장이 거의 마찰 없이 이어진다. 한 번의 터치로 이미지가 쌓이고, 음악과 장소와 상품과 방 사진이 서로 다른 서비스에 일생의 작은 자취를 만든다."
        },
        {
          "type": "paragraph",
          "text": "이 흔적은 설문보다 풍부하지만, 그 자체로 사람은 아니다."
        },
        {
          "type": "paragraph",
          "text": "저장한 이미지가 모두 원하는 삶을 뜻하지는 않는다. 어떤 이미지는 순수한 호기심이고, 어떤 것은 선물을 위한 참고이며, 어떤 것은 그날의 기분이다. 사람은 자신이 실제로 살고 싶은 방이 아니라 잠시 보고 싶은 방을 저장하기도 한다. 알고리즘이 반복해서 보여 줘 익숙해진 이미지를 좋아한다고 착각할 수도 있다."
        },
        {
          "type": "paragraph",
          "text": "따라서 취향의 흔적을 읽는 일은 데이터를 많이 모으는 일과 같지 않다. 맥락을 묻는 일이 필요하다."
        },
        {
          "type": "paragraph",
          "text": "왜 이것을 저장했는가. 여기서 무엇이 가장 먼저 보였는가. 이 장소를 그리워하는가, 아니면 그곳에서의 자신을 그리워하는가. 이 색을 방 전체에 원하는가, 작은 지점으로 원하는가. 좋아하지만 함께 살고 싶지는 않은 것은 무엇인가."
        },
        {
          "type": "paragraph",
          "text": "좋은 질문은 흔적을 증거로 바꾼다."
        },
        {
          "type": "paragraph",
          "text": "여기서 개인정보와 신뢰의 문제가 생긴다. 취향의 흔적은 사소해 보이지만 매우 개인적이다. 여행, 관계, 기억, 구매력, 생활 공간이 함께 드러날 수 있다. 기술적으로 접근 가능하다는 사실이 윤리적으로 사용해도 된다는 허락은 아니다. 공간번역이 신뢰받으려면 필요한 자료만 받고, 왜 필요한지 설명하고, 사용자가 지우고 통제할 수 있어야 한다."
        },
        {
          "type": "paragraph",
          "text": "우리의 목표는 사람을 데이터로 환원하는 것이 아니다. 데이터가 사람에게 더 나은 질문을 던지게 하는 것이다."
        },
        {
          "type": "paragraph",
          "text": "취향의 흔적이 원문이라면, 방은 번역될 문맥이다. 최근까지 컴퓨터는 이 둘을 한 자리에서 다루는 데 서툴렀다. 텍스트는 텍스트대로, 이미지는 이미지대로 처리했다. 이제 그 경계가 느슨해지고 있다."
        }
      ]
    },
    {
      "id": "base-08",
      "kind": "chapter",
      "originalNumber": 8,
      "title": "방을 읽는 기계가 나타났다",
      "blocks": [
        {
          "type": "paragraph",
          "text": "빈 방 사진 한 장을 컴퓨터에게 보여 준다고 생각해 보자."
        },
        {
          "type": "paragraph",
          "text": "몇 년 전만 해도 기계가 잘하는 일은 사진 속 사물에 이름을 붙이는 것이었다. 소파, 창문, 테이블, 식물. 오늘날의 비전 모델은 사물뿐 아니라 형태, 색, 질감, 배치 같은 시각 요소를 분석하고, 텍스트와 여러 이미지를 함께 입력받아 새로운 이미지를 만들거나 기존 이미지를 편집할 수 있다.〔7〕 Google은 다중 이미지 결합의 예로 사물을 장면에 넣거나 색상과 질감에 맞춰 방을 다시 꾸미는 작업을 직접 제시했다.〔8〕"
        },
        {
          "type": "paragraph",
          "text": "이 변화는 공간 개인화의 기술적 바닥을 바꾼다."
        },
        {
          "type": "paragraph",
          "text": "이전의 추천 시스템은 대개 사람과 상품을 연결했다. 이 상품을 본 사람이 저 상품도 보았다는 관계다. 공간번역에는 세 번째 항이 필요하다. 사람과 상품 사이에 실제 방이 들어와야 한다. 아무리 취향에 맞는 작품도 벽의 비율, 주변 색, 빛과 맞지 않으면 좋은 선택이 아니기 때문이다."
        },
        {
          "type": "paragraph",
          "text": "방을 읽는 기계는 이 세 번째 항을 다룰 가능성을 연다."
        },
        {
          "type": "paragraph",
          "text": "가령 방 사진에서 비어 있는 벽의 대략적인 비율을 보고, 기존 가구의 주된 색과 재료를 파악하고, 작품을 놓았을 때 주변과 어떤 대비가 생기는지 시각화할 수 있다. 사용자가 제공한 여러 참고 이미지에서 공통적인 색과 질감을 찾고, 실제 방 안에서 서로 다른 방향을 비교해 보여 줄 수 있다."
        },
        {
          "type": "paragraph",
          "text": "그러나 읽는다는 말을 조심해서 사용해야 한다."
        },
        {
          "type": "paragraph",
          "text": "기계가 갈색 의자와 오후의 빛을 인식한다고 해서 그 의자가 할머니의 것이었다는 사실을 아는 것은 아니다. 바다 사진을 분석한다고 해서 그 장소가 회복의 기억인지 상실의 기억인지 이해하지 못한다. 시각 모델은 이미지에서 패턴을 다루지만, 한 사람의 삶에서 무엇이 중요한지는 질문과 대화로 확인해야 한다."
        },
        {
          "type": "paragraph",
          "text": "기계는 방을 볼 수 있다. 의미를 보장하지는 못한다."
        },
        {
          "type": "paragraph",
          "text": "이 한계를 인정하면 역할 분담이 선명해진다. 기계는 반복적인 시각 분석과 빠른 조합, 다양한 시안의 구현을 맡을 수 있다. 사람은 어떤 단서가 중요한지 말하고, 해석이 자신과 맞는지 판단한다. 서비스는 그 둘 사이에서 질문을 설계하고, 결과를 줄이고, 실제 구매에 필요한 정보를 제공한다."
        },
        {
          "type": "paragraph",
          "text": "이것은 자동화의 서사라기보다 협업의 서사에 가깝다."
        },
        {
          "type": "paragraph",
          "text": "공간번역의 품질은 모델이 얼마나 놀라운 그림을 만드느냐만으로 결정되지 않는다. 입력 질문이 얼마나 세심한지, 방의 제약을 얼마나 정확히 반영하는지, 결과 사이에 의미 있는 차이가 있는지, 사용자가 왜 이런 결과가 나왔는지 이해하는지가 함께 중요하다."
        },
        {
          "type": "paragraph",
          "text": "기술 회사는 흔히 가능성을 시연한다. 방의 색을 한 번에 바꾸고, 가구를 옮기고, 새로운 작품을 만들어 낸다. 시연은 미래를 보여 주지만 일상은 시연 뒤에 시작된다. 화면에서 가능한 것이 벽에 걸 수 있는 물건이 되려면 크기, 인쇄, 프레임, 색 재현, 가격, 배송이라는 오래된 세계를 통과해야 한다."
        },
        {
          "type": "paragraph",
          "text": "공간번역이 실제 삶에 들어오려면 픽셀이 물건이 되어야 한다."
        }
      ]
    },
    {
      "id": "base-09",
      "kind": "chapter",
      "originalNumber": 9,
      "title": "단 하나도 생산할 수 있게 되었다",
      "blocks": [
        {
          "type": "paragraph",
          "text": "전통적인 대량생산은 미래의 평균적인 고객을 상상한다. 얼마나 팔릴지 예측하고, 같은 물건을 많이 만들고, 창고에 보관한 뒤, 그 물건을 원하는 사람을 찾는다. 예측이 맞으면 가격이 낮아진다. 틀리면 재고가 남는다."
        },
        {
          "type": "paragraph",
          "text": "개인화는 이 질서와 잘 맞지 않았다. 사람마다 다른 결과를 미리 대량으로 만들 수 없기 때문이다. 맞춤 제작은 가능했지만 대개 시간과 비용이 많이 들었다. 한쪽에는 저렴하지만 일반적인 상품이, 다른 쪽에는 특별하지만 비싼 서비스가 있었다."
        },
        {
          "type": "paragraph",
          "text": "주문형 생산은 순서를 뒤집는다. 고객이 먼저 선택하고, 그 뒤에 물건이 태어난다."
        },
        {
          "type": "paragraph",
          "text": "오늘날의 주문형 인쇄 서비스는 선결제 재고나 최소 주문 수량 없이 주문이 들어올 때 한 개의 제품도 생산할 수 있다고 안내한다. 일부 네트워크는 고객과 가까운 생산 파트너에게 주문을 보내는 구조도 갖추고 있다.〔9〕 모든 품질과 비용 문제가 해결되었다는 뜻은 아니다. 중요한 것은 하나의 결과를 실물로 만드는 일이 더 이상 예외적인 공예 프로젝트만은 아니라는 점이다."
        },
        {
          "type": "paragraph",
          "text": "이 변화는 개인화의 경제학을 바꾼다."
        },
        {
          "type": "paragraph",
          "text": "과거에는 먼저 만들어야 팔 수 있었다. 이제는 먼저 해석하고 선택받은 뒤 만들 수 있다. 재고 위험이 줄어들면 더 작은 고객 집단과 더 다양한 결과를 다룰 수 있다. 대량생산의 평균에 맞지 않는 취향도 상품이 될 가능성이 생긴다."
        },
        {
          "type": "paragraph",
          "text": "하지만 주문형 생산을 마법처럼 말해서는 안 된다."
        },
        {
          "type": "paragraph",
          "text": "화면의 색과 종이의 색은 다르다. 프레임의 재질은 사진 한 장으로 완전히 알 수 없다. 국가별 규격과 세금, 배송비, 파손과 반품이 있다. 가까운 곳에서 생산한다고 해도 원재료와 물류의 환경 비용은 남는다. 생성된 이미지의 저작권과 원본성, 인쇄 해상도, 장기 보존성도 검토해야 한다."
        },
        {
          "type": "paragraph",
          "text": "개인화된 이미지가 많아질수록 물성에 대한 책임은 오히려 커진다."
        },
        {
          "type": "paragraph",
          "text": "사람은 파일과 함께 살지 않는다. 종이의 표면, 유리의 반사, 프레임의 두께, 벽에서 보이는 실제 크기와 함께 산다. 화면에서는 아름다웠던 결과도 작게 인쇄하면 힘을 잃고, 조명이 비치면 보이지 않을 수 있다. 공간번역의 마지막 단계는 배송이 아니라 안착이다. 물건이 방에 도착해 주변과 관계를 맺어야 한다."
        },
        {
          "type": "paragraph",
          "text": "여기서 기술과 제조가 만난다. 기계가 사람과 방을 읽고 결과를 만들 수 있다는 사실만으로는 시장이 생기지 않는다. 그 결과를 신뢰할 수 있는 물건으로 바꾸고, 적절한 가격과 시간 안에 전달할 수 있어야 한다."
        },
        {
          "type": "paragraph",
          "text": "취향의 흔적, 방을 읽는 기술, 하나를 만드는 생산. 세 조건이 모였다."
        },
        {
          "type": "paragraph",
          "text": "그런데 한 가지 문제가 더 남는다. 만들 수 있는 결과가 너무 많아졌다는 사실이다."
        }
      ]
    },
    {
      "id": "base-10",
      "kind": "chapter",
      "originalNumber": 10,
      "title": "무한 생성이 만든 선택 빈곤",
      "blocks": [
        {
          "type": "paragraph",
          "text": "생성형 AI에게 따뜻하고 세련된 추상화를 요청하면 몇 초 안에 결과가 나온다. 마음에 들지 않으면 다시 만들면 된다. 색을 바꾸고, 구도를 바꾸고, 화풍을 바꾸고, 수십 번 변형할 수 있다. 과거에는 결과를 만드는 일이 비쌌다. 이제는 멈추는 일이 어렵다."
        },
        {
          "type": "paragraph",
          "text": "첫 번째 결과보다 두 번째가 나을 수 있다. 그렇다면 스무 번째는 더 낫지 않을까. 한 번 더 누르는 비용이 거의 없을 때, 우리는 언제 선택해야 하는지 알기 어렵다."
        },
        {
          "type": "paragraph",
          "text": "풍요는 자유를 주지만 끝을 주지는 않는다."
        },
        {
          "type": "paragraph",
          "text": "선택지가 많으면 언제나 나쁘다는 주장은 사실이 아니다. 사람은 다양한 선택을 원하고, 선택지가 늘면 자신에게 맞는 결과를 찾을 가능성도 커진다. 선택 과잉 연구의 결과도 모든 상황에서 같지 않다. 메타분석은 선택지의 수만이 아니라 선택의 복잡성, 과제의 난도, 자신의 선호에 대한 불확실성, 결정 목적이 과잉 효과를 좌우한다고 정리한다.〔10〕"
        },
        {
          "type": "paragraph",
          "text": "이 조건들은 작품 선택과 묘하게 겹친다."
        },
        {
          "type": "paragraph",
          "text": "작품은 속성을 객관적으로 비교하기 어렵다. 정답이 없고, 취향에 대한 확신이 낮을 수 있으며, 실제 방에서 어떻게 보일지 상상해야 한다. 한 번 고르면 오랫동안 눈에 들어오고, 반품도 번거롭다. 결과의 수보다 비교해야 할 의미의 수가 많다."
        },
        {
          "type": "paragraph",
          "text": "그래서 우리는 선택 빈곤이라는 말을 사용할 수 있다."
        },
        {
          "type": "quote",
          "text": "선택 빈곤은 선택지가 부족한 상태가 아니다. 선택할 기준과 선택 뒤의 확신이 부족한 상태다."
        },
        {
          "type": "paragraph",
          "text": "무한 생성은 선택 빈곤을 해결하는 것처럼 보이지만 악화시킬 수도 있다. 모든 것을 바꿀 수 있다면 어떤 결과도 필연적으로 느껴지지 않는다. 이 파란색을 선택해도 바로 다음 파란색이 있다. 한 결과를 사랑하기보다 아직 보지 못한 결과를 의심하게 된다."
        },
        {
          "type": "paragraph",
          "text": "생성의 시대에 희소해지는 것은 이미지가 아니다. 이유다."
        },
        {
          "type": "paragraph",
          "text": "왜 이 색인가. 왜 이 크기인가. 왜 이 방에서 이 구도인가. 왜 이것이 다른 수십 개보다 나와 더 가까운가. 결과가 이 질문에 답하지 못하면 개인화는 사용자의 이름표를 붙인 우연이 된다."
        },
        {
          "type": "paragraph",
          "text": "따라서 개인화의 다음 경쟁은 얼마나 많이 만들어 주느냐가 아니라 얼마나 잘 줄여 주느냐에서 벌어질 수 있다. 단, 줄이는 방식이 중요하다. 인기순으로 세 개를 보여 주는 것은 큐레이션이 아니다. 서로 다른 해석 논리를 가진 소수의 방향을 제시하고, 각 방향이 어떤 단서와 공간 조건에서 나왔는지 설명해야 한다."
        },
        {
          "type": "paragraph",
          "text": "세 개가 마법의 숫자라는 뜻은 아니다. 하나는 독단적일 수 있고, 무한은 피곤할 수 있다. 세 개는 차이를 느끼면서도 비교할 수 있는 제품 가설이다. 실제 사용자의 선택률과 만족을 통해 바뀔 수 있다."
        },
        {
          "type": "paragraph",
          "text": "좋은 큐레이션은 선택권을 빼앗지 않는다. 선택할 수 있게 만든다."
        },
        {
          "type": "paragraph",
          "text": "이제 Why Now의 네 조건이 완성된다."
        },
        {
          "type": "paragraph",
          "text": "사람은 취향의 흔적을 남긴다. 기계는 방과 참고 이미지를 함께 다룬다. 생산은 하나의 결과도 물건으로 만든다. 큐레이션은 무한한 생성에서 결정 가능한 몇 가지를 남긴다."
        },
        {
          "type": "paragraph",
          "text": "공간번역은 이 네 변화의 교차점에서 태어난다."
        },
        {
          "type": "paragraph",
          "text": "그렇다면 이 변화를 가장 먼저 필요로 하고, 가장 먼저 받아들일 사람은 누구일까. 여기서 우리는 조심해야 한다. 시장은 사람을 쉽게 성별과 나이로 잘라 놓지만, 문제는 그렇게 반듯하게 나뉘지 않기 때문이다."
        }
      ]
    },
    {
      "id": "part-4",
      "kind": "part",
      "originalNumber": 4,
      "title": "먼저 도착한 사람들",
      "blocks": []
    },
    {
      "id": "base-11",
      "kind": "chapter",
      "originalNumber": 11,
      "title": "여성은 시장이 아니라 신호다",
      "blocks": [
        {
          "type": "paragraph",
          "text": "왜 여성인가?"
        },
        {
          "type": "paragraph",
          "text": "이 질문에는 두 가지 나쁜 답이 있다."
        },
        {
          "type": "paragraph",
          "text": "첫 번째는 여성은 원래 집 꾸미기를 좋아한다는 답이다. 간단하고 익숙하지만 설명이라기보다 고정관념이다. 돌봄과 가사와 미적 의사결정을 여성의 본성으로 돌리면, 누가 왜 그런 역할을 맡아 왔는지 지워진다. 남성이나 성별 범주 밖의 고객이 같은 문제를 겪는다는 사실도 보지 못한다."
        },
        {
          "type": "paragraph",
          "text": "두 번째는 여성 시장이 크기 때문이라는 답이다. 시장 규모는 출발의 이유가 될 수 있지만, 문제와 고객이 왜 만나는지는 설명하지 못한다. 숫자가 큰 집단을 고르는 것과 강한 필요가 있는 집단을 발견하는 것은 다른 일이다."
        },
        {
          "type": "paragraph",
          "text": "우리가 여성에게서 시작하려는 이유는 더 제한적이다."
        },
        {
          "type": "quote",
          "text": "공간번역의 초기 행동 신호가 현재 여성 집단에서 더 선명하게 관찰되기 때문이다."
        },
        {
          "type": "paragraph",
          "text": "첫 번째 신호는 발견 채널에 있다. Pinterest가 공개한 전 세계 이용자 구성은 여성 70%, 남성 30%다.〔11〕 이 수치만으로 여성이 집을 더 중요하게 여긴다고 말할 수는 없다. Pinterest는 집뿐 아니라 패션, 음식, 여행, 뷰티, 행사 기획 등 다양한 행동을 담는다. 공개된 두 범주의 수치가 성별의 다양성을 충분히 설명하지 못한다는 한계도 있다. 다만 이미지를 저장하고 미래의 선택을 계획하는 장소에 여성이 많이 모여 있다는 것은 이 책이 다루는 취향의 흔적을 발견하기에 중요한 조건이다."
        },
        {
          "type": "paragraph",
          "text": "두 번째 신호는 독립적인 주거 의사결정에 있다. 미국 NAR의 2025년 조사에서 첫 주택 구매자 가운데 싱글 여성은 25%, 싱글 남성은 10%였다.〔12〕 이것도 전체 여성의 성향을 설명하는 숫자는 아니다. NAR 자료는 미국에서 실제 주택을 구매한 사람을 다루며 임차인이나 다른 국가를 대표하지 않는다. 그러나 여성 혼자서도 큰 주거 결정을 내리는 집단이 무시하기 어려운 규모로 존재한다는 사실은 보여 준다."
        },
        {
          "type": "paragraph",
          "text": "세 번째 신호는 이야기의 방식에 있다. 집을 새 출발, 회복, 독립, 관계의 변화와 연결해 말하는 콘텐츠에서 여성의 목소리는 자주 전면에 등장한다. 이 신호는 앞의 두 통계보다 측정이 어렵다. 그래서 확정된 사실보다 조사해야 할 가설에 가깝다. 실제 인터뷰와 콘텐츠 분석을 통해 확인해야 한다."
        },
        {
          "type": "paragraph",
          "text": "세 신호를 합치면 초기 고객의 초상이 생긴다. 시각적 자료를 저장하고, 집에 관한 의사결정에 관여하며, 공간을 생애 변화의 언어로 사용하는 사람이다. 현재 그 초상이 여성에게 더 자주 보인다는 것이지, 문제의 본질이 여성이라는 뜻은 아니다."
        },
        {
          "type": "paragraph",
          "text": "여성은 시장의 경계가 아니라 시장을 발견하게 하는 신호다."
        },
        {
          "type": "paragraph",
          "text": "이 구분은 제품 설계에도 영향을 준다. 여성용 아트를 만들려고 하면 분홍색, 부드러운 곡선, 특정한 감성 문구 같은 낡은 평균으로 미끄러지기 쉽다. 그러나 여성에게서 관찰된 행동을 설계하면 질문이 달라진다. 저장한 이미지와 실제 방의 간극을 어떻게 줄일 것인가. 생애 전환을 어떻게 민감하게 물을 것인가. 개인적인 기억을 안전하게 다룰 것인가. 결과를 쉽게 비교하고 확신 있게 선택하게 할 것인가."
        },
        {
          "type": "paragraph",
          "text": "이 질문들은 성별을 넘어 유효하다."
        },
        {
          "type": "paragraph",
          "text": "따라서 women-led라는 표현은 여성만 받겠다는 문구가 아니다. 초기 사용자 연구와 브랜드 이야기를 여성 중심으로 시작하되, 제품은 자신다운 집을 원하는 누구에게나 열어 두겠다는 전략이다. 초기 데이터에서 남성이나 성별 중립 집단이 같은 문제 강도와 더 높은 선택률을 보인다면 타깃 설명은 바뀌어야 한다."
        },
        {
          "type": "paragraph",
          "text": "여기에는 현실적인 위험도 있다. 여성 중심 채널에서 시작하면 여성의 행동만 더 많이 보이고, 그 결과 다시 여성을 핵심 고객으로 확신하는 순환이 생길 수 있다. 관찰한 것을 타깃으로 삼았는데, 타깃으로 삼았기 때문에 그것만 관찰하게 되는 것이다."
        },
        {
          "type": "paragraph",
          "text": "이를 피하려면 비교군이 필요하다. 같은 주거 전환을 겪는 남성, 커플, 44세 이상 고객, 성별 정체성이 다양한 고객에게 동일한 질문을 던져야 한다. 성별보다 이사 시점이나 취향 저장 행동이 구매를 더 잘 예측하는지 확인해야 한다."
        },
        {
          "type": "paragraph",
          "text": "좋은 타기팅은 사람을 좁게 보는 기술이 아니다. 어떤 차이가 실제로 중요한지 배우는 기술이다."
        },
        {
          "type": "paragraph",
          "text": "성별보다 더 강력할 가능성이 있는 차이가 하나 있다. 나이가 아니라 삶이 바뀐 순간이다."
        }
      ]
    },
    {
      "id": "base-12",
      "kind": "chapter",
      "originalNumber": 12,
      "title": "나이보다 생애 전환이 먼저다",
      "blocks": [
        {
          "type": "paragraph",
          "text": "사업계획서의 고객은 지나치게 정확하다. 스물아홉 살이고, 대도시에 살고, 일정한 소득이 있으며, 특정 플랫폼을 사용하고, 특정한 말투로 불편을 호소한다. 현실의 고객은 생일이 지나면 갑자기 다른 사람이 되지 않는다."
        },
        {
          "type": "paragraph",
          "text": "초기 가설로 28~43세를 잡는 데에는 근거가 있다. 20대 후반부터 40대 초반은 온라인 구매와 시각적 탐색 행동이 활발하고, 독립, 장기 임대, 동거, 첫 주택 구매, 이별 후 재정착, 가족 구성과 같은 주거 전환이 겹치는 시기다. 유럽의 2025년 전자상거래 자료에서도 25~34세의 온라인 구매 비율이 가장 높고 35~44세가 뒤를 이었다.〔13〕 Pinterest의 미국 도달 자료 역시 25~34세와 35~44세에서 모두 높은 수준을 보인다.〔11〕"
        },
        {
          "type": "paragraph",
          "text": "그러나 이 범위를 정답으로 만들면 자료가 오히려 현실을 가린다."
        },
        {
          "type": "paragraph",
          "text": "미국의 첫 주택 구매자 중위 연령이 40세라는 사실은 첫 집 고객은 30대 초반이라는 오래된 이미지를 흔든다.〔3〕 캐나다에서는 높은 주거비와 변화한 가족 형성 시점 때문에 25~39세의 주거 경로가 이전 세대보다 다양해졌다.〔4〕 영국의 민간 임대 가구에서도 35~44세 가구 대표자(HRP)는 작지 않은 비중을 차지한다.〔5〕 안정된 성인 주거를 처음 만드는 시기는 한 방향으로만 이동하지 않는다."
        },
        {
          "type": "paragraph",
          "text": "나이는 달력이다. 전환은 동사다."
        },
        {
          "type": "paragraph",
          "text": "사람이 홈데코를 찾는 이유를 더 잘 설명하는 것은 몇 살인가보다 무슨 일이 일어났는가일 수 있다."
        },
        {
          "type": "paragraph",
          "text": "이사했다. 함께 살기 시작했다. 혼자 살게 되었다. 집에서 일하게 되었다. 오랫동안 미뤘던 집을 샀다. 아이가 방을 옮겼다. 새로운 도시에서 다시 시작했다. 당분간 이곳을 떠나지 않기로 했다."
        },
        {
          "type": "paragraph",
          "text": "이 동사들은 현재 공간과 현재의 자신 사이에 틈을 만든다. 이전의 방은 이전의 삶에는 맞았지만 지금의 삶을 설명하지 못한다. 사람이 물건을 바꾸는 이유는 물건이 낡아서만이 아니다. 의미가 낡았기 때문이다."
        },
        {
          "type": "paragraph",
          "text": "따라서 공간번역의 핵심 고객은 다음처럼 정의하는 편이 더 정확하다."
        },
        {
          "type": "quote",
          "text": "주거 전환기에 있으며, 취향의 단서는 충분히 갖고 있지만 그것을 실제 방의 결정으로 옮기지 못하는 도시 생활자."
        },
        {
          "type": "paragraph",
          "text": "이 정의에는 성별도 나이도 소유 여부도 없다. 대신 문제와 행동이 있다."
        },
        {
          "type": "paragraph",
          "text": "그 사람은 마음에 드는 방과 작품과 색을 저장한다. 개별 이미지를 보면 좋고 싫음을 알지만, 자신의 방에 놓을 하나를 고를 때는 확신이 줄어든다. 디자이너를 고용할 만큼 큰 프로젝트는 아니지만 일반적인 상품 추천으로는 부족하다. 직접 생성해 볼 수는 있어도 무한한 결과를 관리하고 싶지는 않다. 예쁜 것보다 자신에게 속한 것을 원한다."
        },
        {
          "type": "paragraph",
          "text": "그리고 그의 삶에는 공간을 다시 보게 만든 사건이 있다."
        },
        {
          "type": "paragraph",
          "text": "28~43세 여성은 이 핵심 정의를 처음 검증하기 위한 관찰 범위다. 핵심 정의 자체가 아니다. 이 차이를 지키면 조사 결과에 따라 인구통계를 바꾸면서도 제품의 문제 정의는 유지할 수 있다."
        },
        {
          "type": "paragraph",
          "text": "예컨대 44~55세의 자녀 독립 이후 고객이 더 강한 지불 의향을 보일 수 있다. 이사 후 6개월 이내의 남성이 예상보다 빠르게 작품을 선택할 수 있다. 첫 자가 여부보다 이별 후 재정착이 훨씬 강한 동기일 수 있다. 이 경우 타깃을 수정하는 것은 실패가 아니라 학습이다."
        },
        {
          "type": "paragraph",
          "text": "타깃은 발견한 진실이 아니라 틀릴 수 있게 써 놓은 예측이어야 한다."
        },
        {
          "type": "paragraph",
          "text": "그렇다면 국가도 같은 방식으로 보아야 한다. 미국, 캐나다, 영국은 우리 고객이 사는 나라라는 결론이 아니라, 한 가설을 가장 먼저 비교해 볼 세 개의 실험실이다."
        }
      ]
    },
    {
      "id": "base-13",
      "kind": "chapter",
      "originalNumber": 13,
      "title": "세 나라라는 첫 실험실",
      "blocks": [
        {
          "type": "paragraph",
          "text": "보편적인 욕구는 곧바로 보편적인 제품이 되지 않는다."
        },
        {
          "type": "paragraph",
          "text": "사람이 자신다운 집을 원한다는 감정은 여러 문화에 존재할 수 있다. 그러나 어떤 질문을 자연스럽다고 느끼는지, 어떤 색과 이미지에 어떤 기억을 연결하는지, 작품을 어떤 크기로 사고 어디에 거는지, 얼마를 지불하고 얼마나 기다리는지는 지역마다 다르다."
        },
        {
          "type": "paragraph",
          "text": "보편성은 번역을 면제해 주지 않는다."
        },
        {
          "type": "paragraph",
          "text": "미국, 캐나다, 영국을 첫 시장으로 보는 가장 큰 이유는 세 나라가 같아서가 아니다. 차이를 가진 채 하나의 영어 제품으로 비교할 수 있기 때문이다. 질문, 고객 지원, 콘텐츠의 기본 언어를 공유하면서도 주거 형태, 구매력, 미감, 배송 조건이 다른 세 시장을 통해 무엇이 보편적이고 무엇이 현지적인지 배울 수 있다."
        },
        {
          "type": "paragraph",
          "text": "온라인 구매가 일상적이라는 공통점도 있다. 미국에서 전자상거래는 2026년 1분기 전체 소매 판매의 16.9%였고 전년 동기 대비 성장률은 전체 소매보다 높았다.〔14〕 캐나다의 2024년 소매 전자상거래 매출은 737억 캐나다달러였으며 전년 대비 9% 증가했다.〔15〕 영국에서는 2025년 인터넷 판매가 전체 소매 판매의 27.5%를 차지했다.〔16〕 집을 촬영하고, 온라인에서 방향을 고르고, 제작된 작품을 배송받는 흐름을 시험할 기본 행동이 이미 존재한다."
        },
        {
          "type": "paragraph",
          "text": "그러나 세 시장은 서로 다른 질문을 던진다."
        },
        {
          "type": "paragraph",
          "text": "미국은 규모와 다양성의 시험이다. 아파트, 콘도, 단독주택의 차이가 크고 도시별 미감과 배송 거리도 넓다. 2024년 미국 인구의 11.8%가 이전 1년 사이 거주지를 옮겼으며, 25~34세의 이동률은 더 나이 든 집단보다 일관되게 높다.〔17〕 주거 전환 고객을 만날 가능성이 큰 동시에, 광고 경쟁과 고객 획득 비용도 높다. 미국에서 통하는 하나의 미감을 찾으려는 시도는 처음부터 잘못된 질문일 수 있다."
        },
        {
          "type": "paragraph",
          "text": "캐나다는 친숙함과 제약의 시험이다. 미국과 디지털 채널과 언어를 상당 부분 공유하지만, 토론토와 밴쿠버 같은 도시의 높은 주거비, 콘도 생활, 국경과 지역에 따른 배송 비용이 다른 조건을 만든다. 캐나다의 20~35세는 2024년 조사에서 고령층보다 주거비 부담을 더 강하게 호소했고, 51%는 가격 상승 때문에 이사 계획이 영향을 받았다고 답했다.〔18〕 집을 소유하지 못했거나 이동을 미룬 사람에게 지금의 집을 나답게 만들라는 제안은 위로가 될 수도, 현실을 외면한 소비 권유가 될 수도 있다. 메시지의 세심함이 시험받는다."
        },
        {
          "type": "paragraph",
          "text": "영국은 번역의 시험이다. 같은 영어를 사용하지만 home, flat, art print, 크기 표기와 인테리어 언어의 감각이 다르다. 공간도 다르다. 영국 민간 임대 부문의 가구 대표자(HRP) 중 25~34세가 32%, 35~44세가 24%였고, 젊은 런던 임차인은 소득에서 임대료가 차지하는 비율이 높다.〔5〕〔19〕 작은 플랫, 오래된 벽, 서로 다른 프레임 규격과 배송 관행은 제품을 그대로 복사할 수 없게 만든다."
        },
        {
          "type": "paragraph",
          "text": "세 나라의 선택에는 실용적인 이유도 있다. 하나의 기본 언어로 브랜드와 제품 흐름을 운영할 수 있다. Pinterest, Instagram, TikTok에서 발견한 이야기를 같은 원고로 시험한 뒤 지역별 반응을 비교할 수 있다. 주문형 생산 파트너와 배송망을 연결할 선택지도 상대적으로 많다."
        },
        {
          "type": "paragraph",
          "text": "하지만 영어라는 편리함이 문화적 동일성을 뜻하지는 않는다. 미국의 고객 사례를 캐나다와 영국에 번역 없이 적용하면, 공간번역을 말하는 브랜드가 정작 시장을 번역하지 못하는 모순에 빠진다."
        },
        {
          "type": "paragraph",
          "text": "그래서 세 나라는 출시 목록이 아니라 질문 목록이어야 한다."
        },
        {
          "type": "paragraph",
          "text": "어느 나라에서 빈 벽의 문제가 가장 강한가. 임차인과 소유자의 선택 기준은 어떻게 다른가. 작품 크기와 가격의 경계는 어디인가. 기억과 취향을 묻는 질문이 자연스러운가, 부담스러운가. 실제 방 미리보기가 구매 확신을 얼마나 높이는가. 배송비와 반품이 개인화의 가치를 지우지는 않는가."
        },
        {
          "type": "paragraph",
          "text": "이 질문의 답에 따라 순서는 바뀔 수 있다. 아일랜드나 호주가 영어권 확장에 더 적합할 수 있고, 네덜란드나 북유럽의 온라인 구매와 디자인 문화가 강한 반응을 보일 수 있다. 반대로 수요가 있어도 현지 제작과 반품 구조가 맞지 않으면 출시를 늦춰야 한다."
        },
        {
          "type": "paragraph",
          "text": "국가는 고객의 본질이 아니다. 학습의 단위다."
        },
        {
          "type": "paragraph",
          "text": "이제 우리는 시대의 조건과 먼저 도착한 사람들을 살펴보았다. 남은 질문은 가장 구체적이다. 한 사람의 기억은 실제로 어떻게 색과 비율이 될 수 있는가."
        }
      ]
    },
    {
      "id": "part-5",
      "kind": "part",
      "originalNumber": 5,
      "title": "나를 공간으로 옮기는 법",
      "blocks": []
    },
    {
      "id": "base-14",
      "kind": "chapter",
      "originalNumber": 14,
      "title": "기억은 어떻게 색과 비율이 되는가",
      "blocks": [
        {
          "type": "paragraph",
          "text": "공간번역은 무엇을 좋아하세요?라고 묻는 데서 시작하지 않는다."
        },
        {
          "type": "paragraph",
          "text": "그 질문은 너무 넓어서 사람을 익숙한 답으로 몰아간다. 파란색, 미니멀, 따뜻한 분위기, 추상화. 모두 유효하지만 아직 얇다. 공간번역은 취향의 이름보다 취향이 생긴 장면을 묻는다."
        },
        {
          "type": "paragraph",
          "text": "어떤 장소에서 시간이 느리게 갔는가. 어떤 음악을 들을 때 방의 공기가 달라지는가. 버리지 못한 물건은 무엇인가. 다시 돌아가고 싶은 때가 있는가. 좋아하지만 집에는 두고 싶지 않은 것은 무엇인가."
        },
        {
          "type": "paragraph",
          "text": "사람은 이런 질문에도 완벽히 답하지 못한다. 완벽할 필요도 없다. 번역에 필요한 것은 자서전 전체가 아니라 반복되는 몇 개의 단서다."
        },
        {
          "type": "paragraph",
          "text": "그 단서를 공간으로 옮기는 과정은 네 단계로 나눌 수 있다."
        },
        {
          "type": "paragraph",
          "text": "첫째, 사물이 아니라 감각을 찾는다."
        },
        {
          "type": "paragraph",
          "text": "바다를 좋아한다는 말에서 파도 그림을 꺼내기 전에 무엇이 좋았는지 묻는다. 끝이 보이지 않는 수평선인가, 몸을 감싸는 소리인가, 햇빛에 부서지는 표면인가, 밤바다의 두려움인가. 같은 명사에서 다른 감각이 나온다."
        },
        {
          "type": "paragraph",
          "text": "둘째, 감각을 시각의 문법으로 바꾼다."
        },
        {
          "type": "paragraph",
          "text": "고요함은 무조건 연한 색이 아니다. 넓은 여백, 낮은 대비, 반복이 적은 구성으로 나타날 수 있다. 활기는 무조건 원색이 아니다. 빠른 리듬, 비대칭, 작은 요소들의 충돌로 표현될 수 있다. 향수는 낡은 필터가 아니라 색의 바램, 가장자리의 불확실함, 시선의 거리로 번역될 수 있다."
        },
        {
          "type": "paragraph",
          "text": "셋째, 방의 반론을 듣는다."
        },
        {
          "type": "paragraph",
          "text": "사람의 단서가 아무리 강해도 방에는 이미 문장이 있다. 짙은 소파, 밝은 바닥, 좁은 벽, 낮은 천장, 오후에만 들어오는 빛. 새 작품은 백지에 등장하지 않는다. 기존 문장에 들어오는 한 구절이다. 어울리기만 해도 안 되고, 혼자 소리쳐도 안 된다."
        },
        {
          "type": "paragraph",
          "text": "넷째, 한 개의 정답 대신 다른 해석을 만든다."
        },
        {
          "type": "paragraph",
          "text": "같은 기억은 여러 방식으로 충실할 수 있다. 장소의 색을 살릴 수도 있고, 그곳에서 느낀 리듬을 살릴 수도 있으며, 현재의 방에 필요한 감정만 가져올 수도 있다. 좋은 번역이 하나뿐이라고 말하는 순간, 번역은 판정이 된다."
        },
        {
          "type": "paragraph",
          "text": "세 사람의 방을 상상해 보자. 이들은 실제 인터뷰 인물이 아니라 번역의 차이를 보여 주기 위한 가상 사례다."
        },
        {
          "type": "subheading",
          "text": "첫 번째 방: 정원을 그리지 않고 회복을 그리는 법"
        },
        {
          "type": "paragraph",
          "text": "런던의 작은 플랫에 사는 마흔 살 레이철은 관계가 끝난 뒤 집에 혼자 남았다. 가구의 절반이 빠져나가자 방은 넓어졌지만 편안해지지는 않았다. 그는 할머니의 온실을 자주 떠올린다고 말했다. 젖은 흙 냄새, 유리창에 맺힌 물, 너무 빠르게 자라 제멋대로 얽힌 줄기. 좋아하는 색은 초록이지만, 잎이 많은 식물 그림은 원하지 않았다."
        },
        {
          "type": "paragraph",
          "text": "가장 쉬운 결과는 온실 사진이나 식물 일러스트레이션이다. 그러나 레이철이 기억하는 핵심은 식물이 아니라 다시 자라는 감각일 수 있다. 그렇다면 번역의 어휘가 달라진다."
        },
        {
          "type": "paragraph",
          "text": "젖은 흙은 갈색 물체가 아니라 깊고 무광인 바탕이 된다. 유리의 물방울은 작은 반사와 투명한 층이 된다. 얽힌 줄기는 화면 밖으로 이어질 듯한 가느다란 선의 성장으로 나타난다. 초록은 방 전체를 덮지 않고 어두운 바탕에서 조금씩 올라온다."
        },
        {
          "type": "paragraph",
          "text": "레이철의 거실에는 회색 소파와 오래된 나무 바닥이 있다. 창이 작아 방은 오후에도 밝지 않다. 작품까지 무겁게 만들면 회복보다 침잠에 가까워질 수 있다. 그래서 충분한 밝은 여백을 남기고, 짙은 색은 아래쪽에 모은다. 기억에 충실하되 방이 필요로 하는 빛을 더한다."
        },
        {
          "type": "paragraph",
          "text": "이 번역의 제목은 온실이 아니라 다시 자라는 쪽으로일 수 있다. 장소의 이름보다 기억의 동사를 남긴다."
        },
        {
          "type": "subheading",
          "text": "두 번째 방: 두 사람의 취향을 평균 내지 않는 법"
        },
        {
          "type": "paragraph",
          "text": "토론토의 콘도로 이사한 서른세 살 마야와 서른다섯 살 샘은 각자의 가구를 합쳤다. 마야는 리스본의 오래된 타일과 햇빛을 좋아한다. 샘은 재즈 음반의 검은 표지와 기하학적인 타이포그래피를 좋아한다. 두 취향을 절충하면 베이지색처럼 무난한 결과가 나오기 쉽다. 누구도 싫어하지 않지만 누구도 사랑하지 않는 색이다."
        },
        {
          "type": "paragraph",
          "text": "공간번역은 둘의 취향에서 공통된 물건보다 공통된 관계를 찾는다."
        },
        {
          "type": "paragraph",
          "text": "리스본의 타일에는 반복되는 격자와 손으로 만든 작은 오차가 있다. 재즈에는 반복되는 박자와 즉흥적인 이탈이 있다. 하나는 시각이고 하나는 소리지만, 둘 다 규칙 속의 어긋남을 공유한다."
        },
        {
          "type": "paragraph",
          "text": "이 공통 문법을 사용하면 타일 그림과 음반 포스터를 섞을 필요가 없다. 규칙적인 격자를 만들고 몇 개의 선만 박자에서 벗어나게 한다. 마야가 기억하는 햇빛은 흰색과 테라코타의 온도로, 샘이 좋아하는 음반의 밀도는 짙은 남색의 작은 면으로 들어간다."
        },
        {
          "type": "paragraph",
          "text": "콘도 거실에는 이미 큰 파란 소파가 있다. 작품의 남색이 소파와 똑같으면 세트처럼 보이고, 너무 다르면 충돌한다. 비슷한 계열이지만 명도와 면적을 달리해 소파가 바탕, 작품이 리듬이 되게 한다."
        },
        {
          "type": "paragraph",
          "text": "이것은 두 취향의 평균이 아니다. 두 사람이 왜 그 대상을 좋아하는지에서 공통 문법을 찾은 결과다."
        },
        {
          "type": "subheading",
          "text": "세 번째 방: 어두운 기억을 밝은 방에 놓는 법"
        },
        {
          "type": "paragraph",
          "text": "브루클린의 장기 임대 아파트에 사는 스물아홉 살 노라는 밤에 수영하는 것을 좋아한다. 검은 물 위로 실내 조명이 길게 흔들리고, 물속에서는 도시 소리가 갑자기 멀어지는 순간을 기억한다. 빠른 전자음악도 좋아한다. 노라는 어둡지만 답답하지 않은 것을 원한다고 말했다."
        },
        {
          "type": "paragraph",
          "text": "밤 수영을 검은색과 파란색으로만 번역하면 작은 방이 더 좁아 보일 수 있다. 노라의 방은 북쪽을 향하고 벽도 넓지 않다. 여기서 중요한 것은 밤의 색보다 물속에서 소리가 멀어지는 감각일 수 있다."
        },
        {
          "type": "paragraph",
          "text": "그 감각은 중심으로 갈수록 요소가 줄어드는 구성, 바깥의 빠른 반복과 안쪽의 조용한 여백으로 옮길 수 있다. 전자음악의 리듬은 가장자리에 작은 간격으로 나타나고, 수면의 빛은 검정 대신 은회색과 선명한 청록의 가는 선이 된다. 어둠을 색의 양이 아니라 주변과 중심의 대비로 표현한다."
        },
        {
          "type": "paragraph",
          "text": "결과는 밤을 그렸지만 방을 어둡게 만들지 않는다."
        },
        {
          "type": "paragraph",
          "text": "세 사례에서 공통으로 한 일은 기억의 대상을 복사하지 않은 것이다. 대신 그 기억이 가진 동사와 관계를 찾았다. 자라난다. 어긋난다. 멀어진다. 동사는 공간으로 옮기기 좋다. 색과 형태가 무엇을 해야 하는지 알려 주기 때문이다."
        },
        {
          "type": "paragraph",
          "text": "그렇다고 모든 기억이 작품이 되어야 하는 것은 아니다. 너무 사적이거나 아직 정리되지 않은 경험을 시각화하는 일은 불편할 수 있다. 서비스가 감정의 깊이를 캐내는 척하며 더 많은 데이터를 요구해서도 안 된다. 사용자가 다루고 싶은 범위를 정하고, 언제든 멈출 수 있어야 한다."
        },
        {
          "type": "paragraph",
          "text": "좋은 공간번역은 사람을 해석의 대상으로 붙잡지 않는다. 선택의 주체로 돌려보낸다."
        },
        {
          "type": "paragraph",
          "text": "그 선택을 돕기 위해 몇 개의 결과가 필요할까. 하나는 너무 단정적이고, 무한은 너무 무책임하다. 우리는 그 사이에 세 개의 방향을 놓아 보려 한다."
        }
      ]
    },
    {
      "id": "base-15",
      "kind": "chapter",
      "originalNumber": 15,
      "title": "세 개의 방향이면 충분하다",
      "blocks": [
        {
          "type": "paragraph",
          "text": "한 개의 결과만 보여 주는 시스템은 자신이 사용자를 정확히 이해했다고 주장한다. 무한한 결과를 보여 주는 시스템은 이해의 책임을 사용자에게 돌려준다."
        },
        {
          "type": "paragraph",
          "text": "하나는 판정이고, 무한은 방치다."
        },
        {
          "type": "paragraph",
          "text": "그 사이에서 ELURA는 세 개의 방향을 시험한다. 세 개는 진리의 숫자가 아니다. 차이를 느낄 만큼 다양하고, 비교할 수 있을 만큼 적은 수라는 현재의 가설이다."
        },
        {
          "type": "paragraph",
          "text": "첫 번째는 기억에 가까운 방향이다."
        },
        {
          "type": "paragraph",
          "text": "사용자가 제공한 장소, 음악, 색, 물건의 정서를 가장 충실히 따른다. 앞 장의 레이철이라면 온실의 습기와 성장, 마야와 샘이라면 규칙 속의 어긋남, 노라라면 밤 수영의 정적을 중심에 둔다. 이 방향은 나를 알아본다는 감각을 시험한다."
        },
        {
          "type": "paragraph",
          "text": "두 번째는 방에 가까운 방향이다."
        },
        {
          "type": "paragraph",
          "text": "기억의 단서를 유지하되 현재 공간의 색, 빛, 비율, 가구와 가장 자연스럽게 연결한다. 작품만 떼어 놓았을 때보다 실제 방 안에서 더 좋아 보이는 방향이다. 이 방향은 여기에 속한다는 감각을 시험한다."
        },
        {
          "type": "paragraph",
          "text": "세 번째는 가능성에 가까운 방향이다."
        },
        {
          "type": "paragraph",
          "text": "사용자가 말한 취향에서 한 걸음 벗어나지만 근거 없는 놀라움은 아니다. 반복해서 고른 단서 안에 아직 말로 표현하지 않은 대비나 색을 찾아 확장한다. 이 방향은 몰랐지만 이것도 나일 수 있다는 감각을 시험한다."
        },
        {
          "type": "paragraph",
          "text": "세 방향은 색만 다른 같은 그림이어서는 안 된다. 해석의 이유가 달라야 한다."
        },
        {
          "type": "paragraph",
          "text": "그리고 반드시 실제 방 안에서 보여 주어야 한다. 흰 화면 위의 작품은 상품이다. 소파와 창과 벽 사이에 놓인 작품은 결정이다. 크기를 비교하고, 프레임의 색을 보고, 시선이 어디에 머무는지 확인할 때 사용자는 아름다움보다 소속감을 판단한다."
        },
        {
          "type": "paragraph",
          "text": "여기서 큐레이션된 확신이라는 개념이 나온다."
        },
        {
          "type": "quote",
          "text": "큐레이션된 확신은 대신 골라 주는 것이 아니라, 스스로 납득하며 고를 수 있도록 가능성을 줄이고 이유를 보이는 경험이다."
        },
        {
          "type": "paragraph",
          "text": "확신은 100%의 확실성이 아니다. 취향에는 정답이 없고, 사람은 바뀌며, 방의 빛도 계절마다 달라진다. 필요한 것은 후회가 절대 없다는 보장이 아니라 이 선택이 우연히 나온 것이 아니라는 이해다."
        },
        {
          "type": "paragraph",
          "text": "ELURA가 시험하려는 경험은 다음과 같다."
        },
        {
          "type": "paragraph",
          "text": "먼저 실제 방을 본다. 빈 벽만 잘라 낸 사진이 아니라 주변 가구와 빛이 함께 보이는 장면이 필요하다. 다음으로 좋아하는 장소, 음악, 기억, 색, 물건을 묻는다. 모든 질문에 답하도록 강요하지 않고, 사용자가 편한 단서부터 받는다."
        },
        {
          "type": "paragraph",
          "text": "그 뒤 단서에서 반복되는 감각을 찾는다. 표면의 키워드를 콜라주하는 대신 빛, 리듬, 밀도, 온도, 여백 같은 시각 문법으로 옮긴다. 실제 방의 조건과 부딪쳐 보고, 서로 다른 해석 논리를 가진 세 방향을 만든다."
        },
        {
          "type": "paragraph",
          "text": "세 방향은 방 안에 배치된 모습과 함께 제시된다. 각 방향에는 짧은 설명이 붙는다. 어떤 단서가 어떻게 반영되었는지, 왜 이 크기와 색이 이 방에 맞는지 말한다. 사용자는 결과를 고르거나 수정하거나 모두 거절할 수 있다."
        },
        {
          "type": "paragraph",
          "text": "선택한 방향은 인쇄와 프레임과 크기를 거쳐 실제 물건이 된다. 여기까지 와야 공간번역은 끝난다. 생성된 파일이 아니라 함께 살 수 있는 결정이 최종 결과이기 때문이다."
        },
        {
          "type": "paragraph",
          "text": "ELURA는 예술 생성기와 다르다고 말하고 싶다. 그러나 그 차이는 문구로 생기지 않는다. 실제 경험에서 증명해야 한다."
        },
        {
          "type": "paragraph",
          "text": "사용자가 제공한 단서를 결과에서 알아보는가. 일반적인 생성 도구보다 선택 시간이 줄어드는가. 세 방향은 충분히 다르면서도 모두 관련 있게 느껴지는가. 실제 방 미리보기가 구매 확신을 높이는가. 제품이 도착한 뒤에도 내 집 같다는 감정이 남는가. 이 질문에 답하지 못한다면 공간번역은 멋진 이름을 붙인 이미지 생성에 불과하다."
        },
        {
          "type": "paragraph",
          "text": "또 하나의 위험이 있다. 개인화가 사람을 과거의 취향에 가두는 것이다. 저장한 것만 반복해서 보여 주면 방은 자아의 표현이 아니라 자아의 감옥이 될 수 있다. 사람은 어제 좋아한 것과 다르게 살 권리가 있다. 그래서 세 번째 방향, 가능성에 가까운 해석이 중요하다. 개인화는 과거를 정확히 복제하는 기술이 아니라 현재의 자신이 다음 선택을 발견하게 하는 기술이어야 한다."
        },
        {
          "type": "paragraph",
          "text": "ELURA는 한 사람을 완전히 이해한다고 주장할 수 없다. 몇 개의 입력으로 정체성을 계산할 수도 없다. 할 수 있는 일은 더 작다. 그러나 작다고 해서 중요하지 않은 것은 아니다."
        },
        {
          "type": "paragraph",
          "text": "좋은 질문을 던지고, 흩어진 단서를 연결하고, 실제 방의 조건을 반영하고, 선택 가능한 수로 줄이고, 그 선택을 물건으로 완성하는 일."
        },
        {
          "type": "paragraph",
          "text": "우리는 그것을 공간번역이라고 부른다."
        },
        {
          "type": "paragraph",
          "text": "ELURA는 완성된 해답이 아니다. 하나의 질문을 제품의 형태로 시험하는 일이다."
        },
        {
          "type": "quote",
          "text": "취향을 발견하는 시대 다음에는, 취향을 삶으로 옮기는 시대가 오지 않을까?"
        }
      ]
    },
    {
      "id": "epilogue",
      "kind": "epilogue",
      "title": "집은 두 번째 자화상이다",
      "blocks": [
        {
          "type": "paragraph",
          "text": "다시 빈 벽 앞에 선 사람에게 돌아가 보자."
        },
        {
          "type": "paragraph",
          "text": "소파는 여전히 같은 자리에 있다. 테이블 위 꽃병의 물은 한 번 바뀌었다. 이사 상자 두 개 중 하나는 사라졌고, 다른 하나는 여전히 현관 옆에 있다. 사람은 새집에 적응할 때조차 완벽하게 효율적이지 않다. 다행스러운 일이다."
        },
        {
          "type": "paragraph",
          "text": "달라진 것은 벽이 아니다. 질문이다."
        },
        {
          "type": "paragraph",
          "text": "전에는 요즘 어떤 그림이 인기일까라고 물었다. 이제는 자신이 반복해서 저장한 장면을 살펴본다. 이상하게도 비슷한 빛이 자주 등장한다. 늦은 오후, 그림자가 길어지고 사물의 가장자리가 부드러워지는 시간이다. 여행 사진에서도 그 시간의 창문을 찍었다. 좋아하는 영화의 한 장면도, 오래된 가족사진도 같은 빛을 품고 있다."
        },
        {
          "type": "paragraph",
          "text": "그는 특정한 그림을 좋아한 것이 아니라, 하루가 잠시 느려지는 방식을 좋아했는지도 모른다."
        },
        {
          "type": "paragraph",
          "text": "이 발견이 곧바로 완벽한 작품을 골라 주지는 않는다. 여전히 색을 비교하고 크기를 재고 가격을 생각해야 한다. 그러나 판단의 기준이 생긴다. 더 이상 남의 거실과 닮았는지 묻지 않는다. 이 결과가 자신이 오래 사랑해 온 시간의 감각을 담고 있는지, 그리고 지금의 방에서 편안히 숨 쉴 수 있는지 묻는다."
        },
        {
          "type": "paragraph",
          "text": "취향은 정답이 아니라 기준이 된다."
        },
        {
          "type": "paragraph",
          "text": "며칠 뒤 벽에는 작품 하나가 걸릴 수도 있다. 아무것도 걸리지 않을 수도 있다. 중요한 것은 구매가 아니다. 빈 벽을 자신의 센스 부족에 대한 증거로 보지 않게 되었다는 것이다. 그 벽은 결정을 재촉하는 결함이 아니라 자신에게 더 나은 질문을 건네는 여백이 된다."
        },
        {
          "type": "paragraph",
          "text": "집은 자화상과 닮았지만 얼굴을 그대로 그리지 않는다. 무엇을 가까이 두는지, 무엇을 비워 두는지, 어떤 빛에서 쉬고 싶은지로 사람을 드러낸다. 한 번 완성되고 끝나는 초상도 아니다. 삶이 바뀌면 다시 편집된다."
        },
        {
          "type": "paragraph",
          "text": "앞으로의 집은 더 많은 물건으로 완성되지 않을 것이다."
        },
        {
          "type": "paragraph",
          "text": "더 정확한 관계로 완성될 것이다."
        },
        {
          "type": "paragraph",
          "text": "사람과 기억의 관계, 기억과 색의 관계, 색과 빛의 관계, 작품과 방의 관계. 그리고 그 모든 관계를 선택한 사람과 집의 관계."
        },
        {
          "type": "paragraph",
          "text": "집은 우리가 사는 곳이다. 동시에 우리가 누구였고, 지금 누구이며, 누구로 살아가고 싶은지를 조용히 연습하는 곳이다."
        },
        {
          "type": "paragraph",
          "text": "그러므로 다음에 빈 벽 앞에서 멈춘다면 스타일의 이름부터 찾지 않아도 된다."
        },
        {
          "type": "paragraph",
          "text": "먼저 물어볼 수 있다."
        },
        {
          "type": "quote",
          "text": "내가 반복해서 사랑해 온 것은 무엇이며, 그것은 이 방에서 어떤 모습이어야 하는가?"
        },
        {
          "type": "paragraph",
          "text": "그 질문이 시작되는 순간, 집은 당신을 번역하기 시작한다."
        }
      ]
    },
    {
      "id": "afterword",
      "kind": "afterword",
      "title": "이 책이 아직 모르는 것",
      "blocks": [
        {
          "type": "paragraph",
          "text": "이 책은 하나의 시대예보이자 제품 가설이다. 예보는 미래를 단정하는 일이 아니라 현재의 여러 신호가 어디를 향하는지 설명하는 일이다. 따라서 다음 질문은 열어 두어야 한다."
        },
        {
          "type": "list",
          "items": [
            "취향을 저장하지만 결정하지 못하는 문제가 실제로 얼마나 자주, 얼마나 강하게 발생하는가.",
            "사람은 자신의 기억과 장소를 제품에 제공하는 일을 편안하게 느끼는가.",
            "세 개의 방향이 하나나 열 개보다 실제로 더 나은 결정을 만드는가.",
            "방 안의 미리보기가 감탄을 넘어 구매와 장기 만족에 영향을 주는가.",
            "여성 28~43세보다 더 강한 필요와 지불 의향을 보이는 집단이 있는가.",
            "미국, 캐나다, 영국의 공통 제품 경험이 문화적 차이를 견딜 수 있는가.",
            "개인화된 작품을 받은 뒤 몇 달이 지나도 나답다는 감정이 유지되는가."
          ]
        },
        {
          "type": "paragraph",
          "text": "이 질문에 답하려면 실제 사람과 실제 방이 필요하다. 출간 전후로 세 나라의 고객 30~45명을 심층 인터뷰하고, 성별과 연령, 임차와 소유, 생애 전환을 비교해야 한다. 하나, 셋, 무한 결과의 선택 행동도 시험해야 한다."
        },
        {
          "type": "paragraph",
          "text": "조사 결과 핵심 고객이나 국가가 바뀐다면 책도 수정되어야 한다. 바뀌지 말아야 할 것은 타깃의 숫자가 아니라 문제를 대하는 태도다."
        },
        {
          "type": "paragraph",
          "text": "사람을 평균으로 가정하지 않을 것. 기술이 이해하지 못하는 것을 이해한다고 말하지 않을 것. 더 많은 결과를 가치로 착각하지 않을 것. 화면에서 끝내지 않고 실제 삶에 도착하는지 확인할 것."
        },
        {
          "type": "paragraph",
          "text": "공간번역이라는 이름은 그 약속을 기억하기 위해 붙였다."
        }
      ]
    }
  ],
  "sources": [
    {
      "number": 1,
      "text": "미국 연방준비제도는 주거가 대부분의 가정에서 가장 큰 지출이며 경제적 결과에 큰 영향을 줄 수 있다고 설명한다. Federal Reserve, Report on the Economic Well-Being of U.S. Households in 2024: Housing",
      "links": [
        {
          "label": "Federal Reserve, Report on the Economic Well-Being of U.S. Households in 2024: Housing",
          "url": "https://www.federalreserve.gov/publications/2025-economic-well-being-of-us-households-in-2024-housing.htm"
        }
      ]
    },
    {
      "number": 2,
      "text": "집을 정체성, 애착, 의존이 결합된 장소로 보는 최근 연구 검토는 다음을 참고했다. Safarkhani, \"Space to Place, Housing to Home\" (2025). 자기표현과 개인 정체성을 집의 핵심 속성으로 본 고전적 연구는 다음과 같다. Smith, \"The Essential Qualities of a Home\" (1994)80196-3)",
      "links": [
        {
          "label": "Safarkhani, \"Space to Place, Housing to Home\" (2025)",
          "url": "https://www.mdpi.com/2071-1050/17/15/6842"
        },
        {
          "label": "Smith, \"The Essential Qualities of a Home\" (1994)",
          "url": "https://doi.org/10.1016/S0272-4944(05"
        }
      ]
    },
    {
      "number": 3,
      "text": "NAR의 2025년 조사에서 첫 주택 구매자의 비중은 21%, 중위 연령은 40세였다. 조사는 2024년 7월부터 2025년 6월 사이 미국의 주거용 주택 구매를 다룬다. National Association of REALTORS, 2025 Profile of Home Buyers and Sellers",
      "links": [
        {
          "label": "National Association of REALTORS, 2025 Profile of Home Buyers and Sellers",
          "url": "https://www.nar.realtor/press-releases/first-time-home-buyer-share-falls-to-historic-low-of-21-median-age-rises-to-40"
        }
      ]
    },
    {
      "number": 4,
      "text": "캐나다 통계청은 2021년 25~39세 밀레니얼 가운데 부모와 한 가족으로 사는 비율이 16.3%로, 같은 나이였던 1991년 베이비붐 세대의 8.2%보다 약 두 배였다고 분석한다. Statistics Canada, \"Millennials in the Canadian housing market\" (2026)",
      "links": [
        {
          "label": "Statistics Canada, \"Millennials in the Canadian housing market\" (2026)",
          "url": "https://www150.statcan.gc.ca/n1/pub/46-28-0001/2026001/article/00001-eng.htm"
        }
      ]
    },
    {
      "number": 5,
      "text": "영국 민간 임대 부문 가구 기준 인물 가운데 25~34세는 32%, 35~44세는 24%였다. Office for National Statistics, \"Private rented sector statistics from across the UK\" (2025)",
      "links": [
        {
          "label": "Office for National Statistics, \"Private rented sector statistics from across the UK\" (2025)",
          "url": "https://www.ons.gov.uk/peoplepopulationandcommunity/housing/articles/privaterentedsectorstatisticsfromacrosstheuk/2025"
        }
      ]
    },
    {
      "number": 6,
      "text": "Pinterest는 2026년 1분기에 전 세계 월간 활성 이용자 6억 3,100만 명, 월간 검색 800억 건 이상, 이 중 약 절반이 상업적 검색이라고 발표했다. Pinterest, Q1 2026 Earnings Presentation",
      "links": [
        {
          "label": "Pinterest, Q1 2026 Earnings Presentation",
          "url": "https://s204.q4cdn.com/369458543/files/doc_earnings/2026/q1/presentation/2026-Q1-IR-Earnings-Presentation.pdf"
        }
      ]
    },
    {
      "number": 7,
      "text": "OpenAI 공식 문서는 최근 모델이 이미지 입력을 분석하고, 텍스트와 이미지 입력을 이용해 이미지를 생성하거나 편집할 수 있다고 설명한다. 비전 모델은 사물, 형태, 색, 질감 등을 다룰 수 있지만 한계도 있음을 명시한다. OpenAI, Images and vision",
      "links": [
        {
          "label": "OpenAI, Images and vision",
          "url": "https://developers.openai.com/api/docs/guides/images-vision"
        }
      ]
    },
    {
      "number": 8,
      "text": "Google은 Gemini 2.5 Flash Image의 다중 이미지 결합 예시로 사물을 장면에 넣고, 색상이나 질감으로 방을 재구성하는 작업을 제시했다. Google Developers Blog, \"Introducing Gemini 2.5 Flash Image\"",
      "links": [
        {
          "label": "Google Developers Blog, \"Introducing Gemini 2.5 Flash Image\"",
          "url": "https://developers.googleblog.com/en/introducing-gemini-2-5-flash-image/"
        }
      ]
    },
    {
      "number": 9,
      "text": "Gelato는 선결제 비용과 최소 주문 수량 없이 주문이 들어올 때 생산하고, 고객과 가까운 생산 파트너를 이용하는 구조를 안내한다. 이는 한 업체의 운영 모델을 보여 주는 사례이며 주문형 생산 산업 전체의 품질을 보증하는 근거는 아니다. Gelato Pricing and Fulfillment",
      "links": [
        {
          "label": "Gelato Pricing and Fulfillment",
          "url": "https://www.gelato.com/pricing"
        }
      ]
    },
    {
      "number": 10,
      "text": "선택 과잉에 관한 99개 관찰, 총 7,202명을 종합한 메타분석은 선택지 복잡성, 결정 과제의 난도, 선호 불확실성, 결정 목표를 조절 요인으로 제시한다. Chernev, Bockenholt and Goodman, \"Choice overload: A conceptual review and meta-analysis\" (2015)",
      "links": [
        {
          "label": "Chernev, Bockenholt and Goodman, \"Choice overload: A conceptual review and meta-analysis\" (2015)",
          "url": "https://doi.org/10.1016/j.jcps.2014.08.002"
        }
      ]
    },
    {
      "number": 11,
      "text": "Pinterest의 비즈니스 대상 페이지는 전 세계 이용자 구성을 여성 70%, 남성 30%로 제시하고, 미국에서 25~34세의 40%, 35~44세의 39%에 도달한다고 밝힌다. 이는 Pinterest가 공개한 광고 도달 자료이며 전체 인구의 실제 사용률과 동일하게 해석해서는 안 된다. Pinterest Business, Audience",
      "links": [
        {
          "label": "Pinterest Business, Audience",
          "url": "https://business.pinterest.com/audience/"
        }
      ]
    },
    {
      "number": 12,
      "text": "NAR의 2025년 자료에서 전체 구매자 중 싱글 여성은 21%, 싱글 남성은 9%였고, 첫 주택 구매자 중에는 각각 25%와 10%였다. National Association of REALTORS, 2025 Profile Highlights PDF",
      "links": [
        {
          "label": "National Association of REALTORS, 2025 Profile Highlights PDF",
          "url": "https://www.nar.realtor/sites/default/files/2025-11/2025-profile-of-home-buyers-and-sellers-highlights-11-04-2025.pdf"
        }
      ]
    },
    {
      "number": 13,
      "text": "Eurostat은 2015~2025년 동안 최근 1년 내 온라인 구매 비율이 25~34세에서 가장 높았고, 35~44세가 두 번째였다고 정리한다. Eurostat, E-commerce statistics for individuals (2025)",
      "links": [
        {
          "label": "Eurostat, E-commerce statistics for individuals (2025)",
          "url": "https://ec.europa.eu/eurostat/statistics-explained/index.php?title=E-commerce_statistics_for_individuals"
        }
      ]
    },
    {
      "number": 14,
      "text": "미국 인구조사국은 2026년 1분기 전자상거래가 전체 소매 판매의 16.9%였고, 전년 동기 대비 9.8% 증가해 전체 소매 판매 증가율 3.9%를 웃돌았다고 발표했다. U.S. Census Bureau, Quarterly Retail E-Commerce Sales, Q1 2026",
      "links": [
        {
          "label": "U.S. Census Bureau, Quarterly Retail E-Commerce Sales, Q1 2026",
          "url": "https://www.census.gov/retail/ecommerce.html"
        }
      ]
    },
    {
      "number": 15,
      "text": "캐나다 통계청은 2024년 소매 전자상거래 매출을 737억 캐나다달러, 전년 대비 증가율을 9.0%로 집계했다. Statistics Canada, Annual retail trade, 2024",
      "links": [
        {
          "label": "Statistics Canada, Annual retail trade, 2024",
          "url": "https://www150.statcan.gc.ca/n1/daily-quotidien/260211/dq260211b-eng.htm"
        }
      ]
    },
    {
      "number": 16,
      "text": "영국 통계청 시계열에서 2025년 인터넷 판매는 전체 소매 판매의 27.5%였다. Office for National Statistics, Internet sales as a percentage of total retail sales",
      "links": [
        {
          "label": "Office for National Statistics, Internet sales as a percentage of total retail sales",
          "url": "https://www.ons.gov.uk/businessindustryandtrade/retailindustry/timeseries/j4mc/drsi"
        }
      ]
    },
    {
      "number": 17,
      "text": "미국 인구조사국은 2024년 인구의 11.8%가 이전 1년 사이 다른 거주지로 이동했다고 집계했다. 리치먼드 연방준비은행은 25~34세의 이동률이 더 나이 든 집단보다 일관되게 높다고 분석했다. U.S. Census Bureau, Migration/Geographic Mobility, Federal Reserve Bank of Richmond, \"Why Is Geographic Mobility Declining?\"",
      "links": [
        {
          "label": "U.S. Census Bureau, Migration/Geographic Mobility",
          "url": "https://www.census.gov/topics/population/migration/guidance/acs-1yr.html"
        },
        {
          "label": "Federal Reserve Bank of Richmond, \"Why Is Geographic Mobility Declining?\"",
          "url": "https://www.richmondfed.org/publications/research/economic_brief/2025/eb_25-19"
        }
      ]
    },
    {
      "number": 18,
      "text": "캐나다 통계청의 2024년 조사에서 20~35세의 59%가 주거 비용 감당을 매우 우려했고, 51%는 가격 상승으로 이사 계획이 영향을 받았다고 답했다. Statistics Canada, \"Housing affordability challenges Canadians face, 2024\"",
      "links": [
        {
          "label": "Statistics Canada, \"Housing affordability challenges Canadians face, 2024\"",
          "url": "https://www150.statcan.gc.ca/n1/daily-quotidien/241119/dq241119b-eng.htm"
        }
      ]
    },
    {
      "number": 19,
      "text": "영국 English Housing Survey 2024-25에서 16~34세 런던 민간 임차 가구는 평균적으로 소득의 47%를 임대료에 사용했다. 이 연령대 전체를 ELURA의 고객으로 간주할 수는 없지만 주거비 압력을 보여 주는 자료다. GOV.UK, English Housing Survey 2024 to 2025: age cohorts",
      "links": [
        {
          "label": "GOV.UK, English Housing Survey 2024 to 2025: age cohorts",
          "url": "https://www.gov.uk/government/statistics/english-housing-survey-2024-to-2025-age-cohorts/english-housing-survey-2024-to-2025-age-cohorts"
        }
      ]
    }
  ]
}
